Workbook

Sheet Calculator
A1: Numbersmith - Mortgage and Loan Payoff Calculator
A2: Sample loaded: $420,000 at 6.5% for 30 years, plus $200 extra every month. Change any blue cell to model your own loan.
A3: For education and planning only, not financial advice.
A5: LOAN | D5: EXTRA PAYMENTS | G5: KEY OUTPUTS
A6: Loan amount | B6: 420000 | D6: Extra monthly payment | E6: 200 | G6: Monthly P&I payment | H6: =ROUND(PMT(B7/12,B8*12,-B6),2) -> 2654.69
A7: Annual interest rate | B7: 0.065 | D7: One-time extra payment amount | E7: 3000 | G7: Total interest, no extras (baseline) | H7: =Baseline!I485 -> 535683.53
A8: Loan term (years) | B8: 30 | D8: One-time extra: which payment # (1-480) | E8: 12 | G8: Total interest, with extras | H8: =Schedule!K485 -> 379328.97
A9: Start date (first payment) | B9: 46296 | D9: Annual lump sum amount | E9: 1000 | G9: Interest saved | H9: =H7-H8 -> 156354.56
D10: Annual lump sum month (1=Jan, 12=Dec) | E10: 12 | G10: Months saved | H10: =COUNTIF(Baseline!D6:D485,">0")-COUNTIF(Schedule!D6:D485,">0") -> 89
D11: Extra monthly starts at payment # (1=now) | E11: 1 | G11: New payoff date | H11: =INDEX(Schedule!B6:B485,COUNTIF(Schedule!D6:D485,">0")) -> 54514
A13: SUMMARY: BASELINE VS. YOUR PLAN
B14: Payoff Date | C14: Months | D14: Total Interest | E14: Total Paid
A15: Original schedule (no extras) | B15: =INDEX(Baseline!B6:B485,COUNTIF(Baseline!D6:D485,">0")) -> 57224 | C15: =COUNTIF(Baseline!D6:D485,">0") -> 360 | D15: =H7 -> 535683.53 | E15: =B6+D15 -> 955683.53
A16: Your plan (with extras) | B16: =H11 -> 54514 | C16: =COUNTIF(Schedule!D6:D485,">0") -> 271 | D16: =H8 -> 379328.97 | E16: =B6+D16 -> 799328.97
A19: COLOR LEGEND
B20: Blue text = you type this (an input).
B21: Black text = calculated automatically by formula. Do not overwrite, it will break the calculation.
A23: Built by Numbersmith with AI assistance. Formulas are open; nothing is hidden or locked.
A24: See the Schedule, Baseline, Refinance, and Biweekly tabs for full detail, and Charts for the visuals.

Sheet Schedule
A1: Schedule - Full Amortization With Extra Payments
A2: Formula-driven month-by-month schedule using the Calculator inputs. Extra payments are capped with MIN so the loan never overshoots a zero balance. The monthly extra begins at the start payment number on the Calculator tab.
A3: Rows run up to 480 months (40 years). Once the balance reaches zero, every later row shows zero.
A5: Payment # | B5: Payment Date | C5: Loan Year | D5: Beginning Balance | E5: Interest | F5: Scheduled Principal | G5: Extra Requested | H5: Extra Applied | I5: Total Payment | J5: Ending Balance | K5: Cumulative Interest
A6: 1 | B6: =Calculator!$B$9 -> 46296 | C6: =ROUNDUP(A6/12,0) -> 1 | D6: =Calculator!$B$6 -> 420000 | E6: =IF(D6<=0,0,ROUND(D6*Calculator!$B$7/12,2)) -> 2275 | F6: =IF(D6<=0,0,ROUND(MIN(D6,Calculator!$H$6-E6),2)) -> 379.69 | G6: =ROUND(IF(A6>=Calculator!$E$11,Calculator!$E$6,0)+IF(A6=Calculator!$E$8,Calculator!$E$7,0)+IF(MONTH(B6)=Calculator!$E$10,Calculator!$E$9,0),2) -> 200 | H6: =IF(D6<=0,0,ROUND(MIN(D6-F6,G6),2)) -> 200 | I6: =ROUND(E6+F6+H6,2) -> 2854.69 | J6: =ROUND(MAX(0,D6-F6-H6),2) -> 419420.31 | K6: =ROUND(E6,2) -> 2275
A7: =A6+1 -> 2 | B7: =EDATE(B6,1) -> 46327 | C7: =ROUNDUP(A7/12,0) -> 1 | D7: =J6 -> 419420.31 | E7: =IF(D7<=0,0,ROUND(D7*Calculator!$B$7/12,2)) -> 2271.86 | F7: =IF(D7<=0,0,ROUND(MIN(D7,Calculator!$H$6-E7),2)) -> 382.83 | G7: =ROUND(IF(A7>=Calculator!$E$11,Calculator!$E$6,0)+IF(A7=Calculator!$E$8,Calculator!$E$7,0)+IF(MONTH(B7)=Calculator!$E$10,Calculator!$E$9,0),2) -> 200 | H7: =IF(D7<=0,0,ROUND(MIN(D7-F7,G7),2)) -> 200 | I7: =ROUND(E7+F7+H7,2) -> 2854.69 | J7: =ROUND(MAX(0,D7-F7-H7),2) -> 418837.48 | K7: =ROUND(E7+K6,2) -> 4546.86
A8: =A7+1 -> 3 | B8: =EDATE(B7,1) -> 46357 | C8: =ROUNDUP(A8/12,0) -> 1 | D8: =J7 -> 418837.48 | E8: =IF(D8<=0,0,ROUND(D8*Calculator!$B$7/12,2)) -> 2268.7 | F8: =IF(D8<=0,0,ROUND(MIN(D8,Calculator!$H$6-E8),2)) -> 385.99 | G8: =ROUND(IF(A8>=Calculator!$E$11,Calculator!$E$6,0)+IF(A8=Calculator!$E$8,Calculator!$E$7,0)+IF(MONTH(B8)=Calculator!$E$10,Calculator!$E$9,0),2) -> 1200 | H8: =IF(D8<=0,0,ROUND(MIN(D8-F8,G8),2)) -> 1200 | I8: =ROUND(E8+F8+H8,2) -> 3854.69 | J8: =ROUND(MAX(0,D8-F8-H8),2) -> 417251.49 | K8: =ROUND(E8+K7,2) -> 6815.56
A9: =A8+1 -> 4 | B9: =EDATE(B8,1) -> 46388 | C9: =ROUNDUP(A9/12,0) -> 1 | D9: =J8 -> 417251.49 | E9: =IF(D9<=0,0,ROUND(D9*Calculator!$B$7/12,2)) -> 2260.11 | F9: =IF(D9<=0,0,ROUND(MIN(D9,Calculator!$H$6-E9),2)) -> 394.58 | G9: =ROUND(IF(A9>=Calculator!$E$11,Calculator!$E$6,0)+IF(A9=Calculator!$E$8,Calculator!$E$7,0)+IF(MONTH(B9)=Calculator!$E$10,Calculator!$E$9,0),2) -> 200 | H9: =IF(D9<=0,0,ROUND(MIN(D9-F9,G9),2)) -> 200 | I9: =ROUND(E9+F9+H9,2) -> 2854.69 | J9: =ROUND(MAX(0,D9-F9-H9),2) -> 416656.91 | K9: =ROUND(E9+K8,2) -> 9075.67
A10: =A9+1 -> 5 | B10: =EDATE(B9,1) -> 46419 | C10: =ROUNDUP(A10/12,0) -> 1 | D10: =J9 -> 416656.91 | E10: =IF(D10<=0,0,ROUND(D10*Calculator!$B$7/12,2)) -> 2256.89 | F10: =IF(D10<=0,0,ROUND(MIN(D10,Calculator!$H$6-E10),2)) -> 397.8 | G10: =ROUND(IF(A10>=Calculator!$E$11,Calculator!$E$6,0)+IF(A10=Calculator!$E$8,Calculator!$E$7,0)+IF(MONTH(B10)=Calculator!$E$10,Calculator!$E$9,0),2) -> 200 | H10: =IF(D10<=0,0,ROUND(MIN(D10-F10,G10),2)) -> 200 | I10: =ROUND(E10+F10+H10,2) -> 2854.69 | J10: =ROUND(MAX(0,D10-F10-H10),2) -> 416059.11 | K10: =ROUND(E10+K9,2) -> 11332.56
A11: =A10+1 -> 6 | B11: =EDATE(B10,1) -> 46447 | C11: =ROUNDUP(A11/12,0) -> 1 | D11: =J10 -> 416059.11 | E11: =IF(D11<=0,0,ROUND(D11*Calculator!$B$7/12,2)) -> 2253.65 | F11: =IF(D11<=0,0,ROUND(MIN(D11,Calculator!$H$6-E11),2)) -> 401.04 | G11: =ROUND(IF(A11>=Calculator!$E$11,Calculator!$E$6,0)+IF(A11=Calculator!$E$8,Calculator!$E$7,0)+IF(MONTH(B11)=Calculator!$E$10,Calculator!$E$9,0),2) -> 200 | H11: =IF(D11<=0,0,ROUND(MIN(D11-F11,G11),2)) -> 200 | I11: =ROUND(E11+F11+H11,2) -> 2854.69 | J11: =ROUND(MAX(0,D11-F11-H11),2) -> 415458.07 | K11: =ROUND(E11+K10,2) -> 13586.21
A12: =A11+1 -> 7 | B12: =EDATE(B11,1) -> 46478 | C12: =ROUNDUP(A12/12,0) -> 1 | D12: =J11 -> 415458.07 | E12: =IF(D12<=0,0,ROUND(D12*Calculator!$B$7/12,2)) -> 2250.4 | F12: =IF(D12<=0,0,ROUND(MIN(D12,Calculator!$H$6-E12),2)) -> 404.29 | G12: =ROUND(IF(A12>=Calculator!$E$11,Calculator!$E$6,0)+IF(A12=Calculator!$E$8,Calculator!$E$7,0)+IF(MONTH(B12)=Calculator!$E$10,Calculator!$E$9,0),2) -> 200 | H12: =IF(D12<=0,0,ROUND(MIN(D12-F12,G12),2)) -> 200 | I12: =ROUND(E12+F12+H12,2) -> 2854.69 | J12: =ROUND(MAX(0,D12-F12-H12),2) -> 414853.78 | K12: =ROUND(E12+K11,2) -> 15836.61
A13: =A12+1 -> 8 | B13: =EDATE(B12,1) -> 46508 | C13: =ROUNDUP(A13/12,0) -> 1 | D13: =J12 -> 414853.78 | E13: =IF(D13<=0,0,ROUND(D13*Calculator!$B$7/12,2)) -> 2247.12 | F13: =IF(D13<=0,0,ROUND(MIN(D13,Calculator!$H$6-E13),2)) -> 407.57 | G13: =ROUND(IF(A13>=Calculator!$E$11,Calculator!$E$6,0)+IF(A13=Calculator!$E$8,Calculator!$E$7,0)+IF(MONTH(B13)=Calculator!$E$10,Calculator!$E$9,0),2) -> 200 | H13: =IF(D13<=0,0,ROUND(MIN(D13-F13,G13),2)) -> 200 | I13: =ROUND(E13+F13+H13,2) -> 2854.69 | J13: =ROUND(MAX(0,D13-F13-H13),2) -> 414246.21 | K13: =ROUND(E13+K12,2) -> 18083.73
A14: =A13+1 -> 9 | B14: =EDATE(B13,1) -> 46539 | C14: =ROUNDUP(A14/12,0) -> 1 | D14: =J13 -> 414246.21 | E14: =IF(D14<=0,0,ROUND(D14*Calculator!$B$7/12,2)) -> 2243.83 | F14: =IF(D14<=0,0,ROUND(MIN(D14,Calculator!$H$6-E14),2)) -> 410.86 | G14: =ROUND(IF(A14>=Calculator!$E$11,Calculator!$E$6,0)+IF(A14=Calculator!$E$8,Calculator!$E$7,0)+IF(MONTH(B14)=Calculator!$E$10,Calculator!$E$9,0),2) -> 200 | H14: =IF(D14<=0,0,ROUND(MIN(D14-F14,G14),2)) -> 200 | I14: =ROUND(E14+F14+H14,2) -> 2854.69 | J14: =ROUND(MAX(0,D14-F14-H14),2) -> 413635.35 | K14: =ROUND(E14+K13,2) -> 20327.56
A15: =A14+1 -> 10 | B15: =EDATE(B14,1) -> 46569 | C15: =ROUNDUP(A15/12,0) -> 1 | D15: =J14 -> 413635.35 | E15: =IF(D15<=0,0,ROUND(D15*Calculator!$B$7/12,2)) -> 2240.52 | F15: =IF(D15<=0,0,ROUND(MIN(D15,Calculator!$H$6-E15),2)) -> 414.17 | G15: =ROUND(IF(A15>=Calculator!$E$11,Calculator!$E$6,0)+IF(A15=Calculator!$E$8,Calculator!$E$7,0)+IF(MONTH(B15)=Calculator!$E$10,Calculator!$E$9,0),2) -> 200 | H15: =IF(D15<=0,0,ROUND(MIN(D15-F15,G15),2)) -> 200 | I15: =ROUND(E15+F15+H15,2) -> 2854.69 | J15: =ROUND(MAX(0,D15-F15-H15),2) -> 413021.18 | K15: =ROUND(E15+K14,2) -> 22568.08
A16: =A15+1 -> 11 | B16: =EDATE(B15,1) -> 46600 | C16: =ROUNDUP(A16/12,0) -> 1 | D16: =J15 -> 413021.18 | E16: =IF(D16<=0,0,ROUND(D16*Calculator!$B$7/12,2)) -> 2237.2 | F16: =IF(D16<=0,0,ROUND(MIN(D16,Calculator!$H$6-E16),2)) -> 417.49 | G16: =ROUND(IF(A16>=Calculator!$E$11,Calculator!$E$6,0)+IF(A16=Calculator!$E$8,Calculator!$E$7,0)+IF(MONTH(B16)=Calculator!$E$10,Calculator!$E$9,0),2) -> 200 | H16: =IF(D16<=0,0,ROUND(MIN(D16-F16,G16),2)) -> 200 | I16: =ROUND(E16+F16+H16,2) -> 2854.69 | J16: =ROUND(MAX(0,D16-F16-H16),2) -> 412403.69 | K16: =ROUND(E16+K15,2) -> 24805.28
A17: =A16+1 -> 12 | B17: =EDATE(B16,1) -> 46631 | C17: =ROUNDUP(A17/12,0) -> 1 | D17: =J16 -> 412403.69 | E17: =IF(D17<=0,0,ROUND(D17*Calculator!$B$7/12,2)) -> 2233.85 | F17: =IF(D17<=0,0,ROUND(MIN(D17,Calculator!$H$6-E17),2)) -> 420.84 | G17: =ROUND(IF(A17>=Calculator!$E$11,Calculator!$E$6,0)+IF(A17=Calculator!$E$8,Calculator!$E$7,0)+IF(MONTH(B17)=Calculator!$E$10,Calculator!$E$9,0),2) -> 3200 | H17: =IF(D17<=0,0,ROUND(MIN(D17-F17,G17),2)) -> 3200 | I17: =ROUND(E17+F17+H17,2) -> 5854.69 | J17: =ROUND(MAX(0,D17-F17-H17),2) -> 408782.85 | K17: =ROUND(E17+K16,2) -> 27039.13
A18: =A17+1 -> 13 | B18: =EDATE(B17,1) -> 46661 | C18: =ROUNDUP(A18/12,0) -> 2 | D18: =J17 -> 408782.85 | E18: =IF(D18<=0,0,ROUND(D18*Calculator!$B$7/12,2)) -> 2214.24 | F18: =IF(D18<=0,0,ROUND(MIN(D18,Calculator!$H$6-E18),2)) -> 440.45 | G18: =ROUND(IF(A18>=Calculator!$E$11,Calculator!$E$6,0)+IF(A18=Calculator!$E$8,Calculator!$E$7,0)+IF(MONTH(B18)=Calculator!$E$10,Calculator!$E$9,0),2) -> 200 | H18: =IF(D18<=0,0,ROUND(MIN(D18-F18,G18),2)) -> 200 | I18: =ROUND(E18+F18+H18,2) -> 2854.69 | J18: =ROUND(MAX(0,D18-F18-H18),2) -> 408142.4 | K18: =ROUND(E18+K17,2) -> 29253.37
... A485: =A484+1 -> 480 | B485: =EDATE(B484,1) -> 60876 | C485: =ROUNDUP(A485/12,0) -> 40 | D485: =J484 -> 0 | E485: =IF(D485<=0,0,ROUND(D485*Calculator!$B$7/12,2)) -> 0 | F485: =IF(D485<=0,0,ROUND(MIN(D485,Calculator!$H$6-E485),2)) -> 0 | G485: =ROUND(IF(A485>=Calculator!$E$11,Calculator!$E$6,0)+IF(A485=Calculator!$E$8,Calculator!$E$7,0)+IF(MONTH(B485)=Calculator!$E$10,Calculator!$E$9,0),2) -> 200 | H485: =IF(D485<=0,0,ROUND(MIN(D485-F485,G485),2)) -> 0 | I485: =ROUND(E485+F485+H485,2) -> 0 | J485: =ROUND(MAX(0,D485-F485-H485),2) -> 0 | K485: =ROUND(E485+K484,2) -> 379328.97

Sheet Baseline
A1: Baseline - Original Schedule, No Extra Payments
A2: The same loan on the Calculator tab with none of the extra payments applied. Used to measure interest saved and months saved.
A3: Rows run up to 480 months (40 years). Once the balance reaches zero, every later row shows zero.
A5: Payment # | B5: Payment Date | C5: Loan Year | D5: Beginning Balance | E5: Interest | F5: Principal | G5: Total Payment | H5: Ending Balance | I5: Cumulative Interest
A6: 1 | B6: =Calculator!$B$9 -> 46296 | C6: =ROUNDUP(A6/12,0) -> 1 | D6: =Calculator!$B$6 -> 420000 | E6: =IF(D6<=0,0,ROUND(D6*Calculator!$B$7/12,2)) -> 2275 | F6: =IF(D6<=0,0,ROUND(MIN(D6,Calculator!$H$6-E6),2)) -> 379.69 | G6: =ROUND(E6+F6,2) -> 2654.69 | H6: =ROUND(MAX(0,D6-F6),2) -> 419620.31 | I6: =ROUND(E6,2) -> 2275
A7: =A6+1 -> 2 | B7: =EDATE(B6,1) -> 46327 | C7: =ROUNDUP(A7/12,0) -> 1 | D7: =H6 -> 419620.31 | E7: =IF(D7<=0,0,ROUND(D7*Calculator!$B$7/12,2)) -> 2272.94 | F7: =IF(D7<=0,0,ROUND(MIN(D7,Calculator!$H$6-E7),2)) -> 381.75 | G7: =ROUND(E7+F7,2) -> 2654.69 | H7: =ROUND(MAX(0,D7-F7),2) -> 419238.56 | I7: =ROUND(E7+I6,2) -> 4547.94
A8: =A7+1 -> 3 | B8: =EDATE(B7,1) -> 46357 | C8: =ROUNDUP(A8/12,0) -> 1 | D8: =H7 -> 419238.56 | E8: =IF(D8<=0,0,ROUND(D8*Calculator!$B$7/12,2)) -> 2270.88 | F8: =IF(D8<=0,0,ROUND(MIN(D8,Calculator!$H$6-E8),2)) -> 383.81 | G8: =ROUND(E8+F8,2) -> 2654.69 | H8: =ROUND(MAX(0,D8-F8),2) -> 418854.75 | I8: =ROUND(E8+I7,2) -> 6818.82
A9: =A8+1 -> 4 | B9: =EDATE(B8,1) -> 46388 | C9: =ROUNDUP(A9/12,0) -> 1 | D9: =H8 -> 418854.75 | E9: =IF(D9<=0,0,ROUND(D9*Calculator!$B$7/12,2)) -> 2268.8 | F9: =IF(D9<=0,0,ROUND(MIN(D9,Calculator!$H$6-E9),2)) -> 385.89 | G9: =ROUND(E9+F9,2) -> 2654.69 | H9: =ROUND(MAX(0,D9-F9),2) -> 418468.86 | I9: =ROUND(E9+I8,2) -> 9087.62
A10: =A9+1 -> 5 | B10: =EDATE(B9,1) -> 46419 | C10: =ROUNDUP(A10/12,0) -> 1 | D10: =H9 -> 418468.86 | E10: =IF(D10<=0,0,ROUND(D10*Calculator!$B$7/12,2)) -> 2266.71 | F10: =IF(D10<=0,0,ROUND(MIN(D10,Calculator!$H$6-E10),2)) -> 387.98 | G10: =ROUND(E10+F10,2) -> 2654.69 | H10: =ROUND(MAX(0,D10-F10),2) -> 418080.88 | I10: =ROUND(E10+I9,2) -> 11354.33
A11: =A10+1 -> 6 | B11: =EDATE(B10,1) -> 46447 | C11: =ROUNDUP(A11/12,0) -> 1 | D11: =H10 -> 418080.88 | E11: =IF(D11<=0,0,ROUND(D11*Calculator!$B$7/12,2)) -> 2264.6 | F11: =IF(D11<=0,0,ROUND(MIN(D11,Calculator!$H$6-E11),2)) -> 390.09 | G11: =ROUND(E11+F11,2) -> 2654.69 | H11: =ROUND(MAX(0,D11-F11),2) -> 417690.79 | I11: =ROUND(E11+I10,2) -> 13618.93
A12: =A11+1 -> 7 | B12: =EDATE(B11,1) -> 46478 | C12: =ROUNDUP(A12/12,0) -> 1 | D12: =H11 -> 417690.79 | E12: =IF(D12<=0,0,ROUND(D12*Calculator!$B$7/12,2)) -> 2262.49 | F12: =IF(D12<=0,0,ROUND(MIN(D12,Calculator!$H$6-E12),2)) -> 392.2 | G12: =ROUND(E12+F12,2) -> 2654.69 | H12: =ROUND(MAX(0,D12-F12),2) -> 417298.59 | I12: =ROUND(E12+I11,2) -> 15881.42
A13: =A12+1 -> 8 | B13: =EDATE(B12,1) -> 46508 | C13: =ROUNDUP(A13/12,0) -> 1 | D13: =H12 -> 417298.59 | E13: =IF(D13<=0,0,ROUND(D13*Calculator!$B$7/12,2)) -> 2260.37 | F13: =IF(D13<=0,0,ROUND(MIN(D13,Calculator!$H$6-E13),2)) -> 394.32 | G13: =ROUND(E13+F13,2) -> 2654.69 | H13: =ROUND(MAX(0,D13-F13),2) -> 416904.27 | I13: =ROUND(E13+I12,2) -> 18141.79
A14: =A13+1 -> 9 | B14: =EDATE(B13,1) -> 46539 | C14: =ROUNDUP(A14/12,0) -> 1 | D14: =H13 -> 416904.27 | E14: =IF(D14<=0,0,ROUND(D14*Calculator!$B$7/12,2)) -> 2258.23 | F14: =IF(D14<=0,0,ROUND(MIN(D14,Calculator!$H$6-E14),2)) -> 396.46 | G14: =ROUND(E14+F14,2) -> 2654.69 | H14: =ROUND(MAX(0,D14-F14),2) -> 416507.81 | I14: =ROUND(E14+I13,2) -> 20400.02
A15: =A14+1 -> 10 | B15: =EDATE(B14,1) -> 46569 | C15: =ROUNDUP(A15/12,0) -> 1 | D15: =H14 -> 416507.81 | E15: =IF(D15<=0,0,ROUND(D15*Calculator!$B$7/12,2)) -> 2256.08 | F15: =IF(D15<=0,0,ROUND(MIN(D15,Calculator!$H$6-E15),2)) -> 398.61 | G15: =ROUND(E15+F15,2) -> 2654.69 | H15: =ROUND(MAX(0,D15-F15),2) -> 416109.2 | I15: =ROUND(E15+I14,2) -> 22656.1
A16: =A15+1 -> 11 | B16: =EDATE(B15,1) -> 46600 | C16: =ROUNDUP(A16/12,0) -> 1 | D16: =H15 -> 416109.2 | E16: =IF(D16<=0,0,ROUND(D16*Calculator!$B$7/12,2)) -> 2253.92 | F16: =IF(D16<=0,0,ROUND(MIN(D16,Calculator!$H$6-E16),2)) -> 400.77 | G16: =ROUND(E16+F16,2) -> 2654.69 | H16: =ROUND(MAX(0,D16-F16),2) -> 415708.43 | I16: =ROUND(E16+I15,2) -> 24910.02
A17: =A16+1 -> 12 | B17: =EDATE(B16,1) -> 46631 | C17: =ROUNDUP(A17/12,0) -> 1 | D17: =H16 -> 415708.43 | E17: =IF(D17<=0,0,ROUND(D17*Calculator!$B$7/12,2)) -> 2251.75 | F17: =IF(D17<=0,0,ROUND(MIN(D17,Calculator!$H$6-E17),2)) -> 402.94 | G17: =ROUND(E17+F17,2) -> 2654.69 | H17: =ROUND(MAX(0,D17-F17),2) -> 415305.49 | I17: =ROUND(E17+I16,2) -> 27161.77
A18: =A17+1 -> 13 | B18: =EDATE(B17,1) -> 46661 | C18: =ROUNDUP(A18/12,0) -> 2 | D18: =H17 -> 415305.49 | E18: =IF(D18<=0,0,ROUND(D18*Calculator!$B$7/12,2)) -> 2249.57 | F18: =IF(D18<=0,0,ROUND(MIN(D18,Calculator!$H$6-E18),2)) -> 405.12 | G18: =ROUND(E18+F18,2) -> 2654.69 | H18: =ROUND(MAX(0,D18-F18),2) -> 414900.37 | I18: =ROUND(E18+I17,2) -> 29411.34
... A485: =A484+1 -> 480 | B485: =EDATE(B484,1) -> 60876 | C485: =ROUNDUP(A485/12,0) -> 40 | D485: =H484 -> 0 | E485: =IF(D485<=0,0,ROUND(D485*Calculator!$B$7/12,2)) -> 0 | F485: =IF(D485<=0,0,ROUND(MIN(D485,Calculator!$H$6-E485),2)) -> 0 | G485: =ROUND(E485+F485,2) -> 0 | H485: =ROUND(MAX(0,D485-F485),2) -> 0 | I485: =ROUND(E485+I484,2) -> 535683.53

Sheet Refinance
A1: Refinance - Break-Even Comparison
A2: Compares staying on the current loan against a proposed refinance. No lender, rate, or product is suggested; enter your own quote.
A5: CURRENT LOAN (from Calculator) | D5: YOUR REFINANCE INPUTS
A6: Original loan amount | B6: =Calculator!$B$6 -> 420000 | D6: Months already paid on current loan | E6: 24
A7: Original interest rate | B7: =Calculator!$B$7 -> 0.065 | D7: Proposed new interest rate | E7: 0.0575
A8: Original term (years) | B8: =Calculator!$B$8 -> 30 | D8: Proposed new term (years) | E8: 30
A9: Current monthly P&I payment | B9: =Calculator!$H$6 -> 2654.69 | D9: Estimated closing costs | E9: 4000
A11: RESULTS
A12: Remaining balance when you refinance | B12: =INDEX(Baseline!H6:H485,E6) -> 410296.59
A13: Remaining interest if you keep the current loan | B13: =Baseline!I485-INDEX(Baseline!I6:I485,E6) -> 481674.38
A14: New monthly P&I payment | B14: =ROUND(PMT(E7/12,E8*12,-B12),2) -> 2394.38
A15: Monthly payment change (new minus current) | B15: =B14-B9 -> -260.31
A16: Total interest on the new loan, full new term | B16: =ROUND(B14*E8*12-B12,2) -> 451680.21
A17: Total cost to refinance (new interest plus closing costs) | B17: =B16+E9 -> 455680.21
A18: Monthly savings if you refinance | B18: =B9-B14 -> 260.31
A19: Break-even month on closing costs | B19: =IF(B18<=0,"No payment savings",ROUNDUP(E9/B18,0)) -> 16
A20: Verdict | B20: =IF(B17<B13,"Refinancing costs less than staying on the current loan.","Keeping the current loan costs less than refinancing.") -> Refinancing costs less than staying on the current loan.
A22: Note: this tab compares total dollars over the remaining loan horizon. It assumes the current loan continues with no extra payments; it does not model the extra-payment plan from the Calculator tab.

Sheet Biweekly
A1: Biweekly - Half-Payments Every Two Weeks
A2: Models paying half the monthly P&I every two weeks. 26 half-payments a year equal 13 full monthly payments instead of 12.
A5: LOAN (from Calculator, not editable here)
A6: Loan amount | B6: =Calculator!$B$6 -> 420000
A7: Annual interest rate | B7: =Calculator!$B$7 -> 0.065
A8: Loan term (years) | B8: =Calculator!$B$8 -> 30
A9: Standard monthly P&I payment | B9: =Calculator!$H$6 -> 2654.69
A11: BIWEEKLY EQUIVALENT
A12: Effective monthly payment (13 payments per year) | B12: =ROUND(B9*13/12,2) -> 2875.91
A13: Months to payoff (NPER) | B13: =NPER(B7/12,-B12,B6) -> 289.83061
A14: Years to payoff | B14: =B13/12 -> 24.152551
A15: Original term (months) | B15: =B8*12 -> 360
A16: Months saved | B16: =B15-B13 -> 70.169388
A17: Total interest paid (biweekly approximation) | B17: =B12*B13-B6 -> 413526.76
A18: Total interest paid (standard baseline) | B18: =Baseline!I485 -> 535683.53
A19: Interest saved | B19: =B18-B17 -> 122156.77
A21: NOTE ON THE SIMPLIFICATION
A22: This tab approximates 26 biweekly half-payments a year as 12 monthly payments of 13/12 times the standard payment, then solves for the new payoff term with NPER. It does not compound every 14 days. The extra cash is the same either way, one additional monthly payment per year, so the true biweekly result is very close to this estimate, usually slightly better since the extra money arrives sooner.

Sheet Charts
A1: Charts - Balance Over Time and Annual Interest vs. Principal
A2: Built automatically from the Schedule and Baseline tabs. Change any blue input on the Calculator tab and both charts update.
A5: CHART 1: LOAN BALANCE OVER TIME (BASELINE VS. WITH EXTRAS)
A28: CHART 2: ANNUAL INTEREST VS. PRINCIPAL, WITH EXTRAS (FROM SCHEDULE, YEAR HELPER + SUMIFS)
A30: Loan Year | B30: Interest | C30: Principal
A31: 1 | B31: =SUMIFS(Schedule!$E$6:$E$485,Schedule!$C$6:$C$485,A31) -> 27039.13 | C31: =SUMIFS(Schedule!$F$6:$F$485,Schedule!$C$6:$C$485,A31)+SUMIFS(Schedule!$H$6:$H$485,Schedule!$C$6:$C$485,A31) -> 11217.15
A32: =A31+1 -> 2 | B32: =SUMIFS(Schedule!$E$6:$E$485,Schedule!$C$6:$C$485,A32) -> 26287.91 | C32: =SUMIFS(Schedule!$F$6:$F$485,Schedule!$C$6:$C$485,A32)+SUMIFS(Schedule!$H$6:$H$485,Schedule!$C$6:$C$485,A32) -> 8968.37
A33: =A32+1 -> 3 | B33: =SUMIFS(Schedule!$E$6:$E$485,Schedule!$C$6:$C$485,A33) -> 25687.3 | C33: =SUMIFS(Schedule!$F$6:$F$485,Schedule!$C$6:$C$485,A33)+SUMIFS(Schedule!$H$6:$H$485,Schedule!$C$6:$C$485,A33) -> 9568.98
A34: =A33+1 -> 4 | B34: =SUMIFS(Schedule!$E$6:$E$485,Schedule!$C$6:$C$485,A34) -> 25046.45 | C34: =SUMIFS(Schedule!$F$6:$F$485,Schedule!$C$6:$C$485,A34)+SUMIFS(Schedule!$H$6:$H$485,Schedule!$C$6:$C$485,A34) -> 10209.83
A35: =A34+1 -> 5 | B35: =SUMIFS(Schedule!$E$6:$E$485,Schedule!$C$6:$C$485,A35) -> 24362.67 | C35: =SUMIFS(Schedule!$F$6:$F$485,Schedule!$C$6:$C$485,A35)+SUMIFS(Schedule!$H$6:$H$485,Schedule!$C$6:$C$485,A35) -> 10893.61
A36: =A35+1 -> 6 | B36: =SUMIFS(Schedule!$E$6:$E$485,Schedule!$C$6:$C$485,A36) -> 23633.11 | C36: =SUMIFS(Schedule!$F$6:$F$485,Schedule!$C$6:$C$485,A36)+SUMIFS(Schedule!$H$6:$H$485,Schedule!$C$6:$C$485,A36) -> 11623.17
A37: =A36+1 -> 7 | B37: =SUMIFS(Schedule!$E$6:$E$485,Schedule!$C$6:$C$485,A37) -> 22854.67 | C37: =SUMIFS(Schedule!$F$6:$F$485,Schedule!$C$6:$C$485,A37)+SUMIFS(Schedule!$H$6:$H$485,Schedule!$C$6:$C$485,A37) -> 12401.61
A38: =A37+1 -> 8 | B38: =SUMIFS(Schedule!$E$6:$E$485,Schedule!$C$6:$C$485,A38) -> 22024.13 | C38: =SUMIFS(Schedule!$F$6:$F$485,Schedule!$C$6:$C$485,A38)+SUMIFS(Schedule!$H$6:$H$485,Schedule!$C$6:$C$485,A38) -> 13232.15
A39: =A38+1 -> 9 | B39: =SUMIFS(Schedule!$E$6:$E$485,Schedule!$C$6:$C$485,A39) -> 21137.96 | C39: =SUMIFS(Schedule!$F$6:$F$485,Schedule!$C$6:$C$485,A39)+SUMIFS(Schedule!$H$6:$H$485,Schedule!$C$6:$C$485,A39) -> 14118.32
A40: =A39+1 -> 10 | B40: =SUMIFS(Schedule!$E$6:$E$485,Schedule!$C$6:$C$485,A40) -> 20192.4 | C40: =SUMIFS(Schedule!$F$6:$F$485,Schedule!$C$6:$C$485,A40)+SUMIFS(Schedule!$H$6:$H$485,Schedule!$C$6:$C$485,A40) -> 15063.88
A41: =A40+1 -> 11 | B41: =SUMIFS(Schedule!$E$6:$E$485,Schedule!$C$6:$C$485,A41) -> 19183.54 | C41: =SUMIFS(Schedule!$F$6:$F$485,Schedule!$C$6:$C$485,A41)+SUMIFS(Schedule!$H$6:$H$485,Schedule!$C$6:$C$485,A41) -> 16072.74
A42: =A41+1 -> 12 | B42: =SUMIFS(Schedule!$E$6:$E$485,Schedule!$C$6:$C$485,A42) -> 18107.13 | C42: =SUMIFS(Schedule!$F$6:$F$485,Schedule!$C$6:$C$485,A42)+SUMIFS(Schedule!$H$6:$H$485,Schedule!$C$6:$C$485,A42) -> 17149.15
A43: =A42+1 -> 13 | B43: =SUMIFS(Schedule!$E$6:$E$485,Schedule!$C$6:$C$485,A43) -> 16958.63 | C43: =SUMIFS(Schedule!$F$6:$F$485,Schedule!$C$6:$C$485,A43)+SUMIFS(Schedule!$H$6:$H$485,Schedule!$C$6:$C$485,A43) -> 18297.65
... A70: =A69+1 -> 40 | B70: =SUMIFS(Schedule!$E$6:$E$485,Schedule!$C$6:$C$485,A70) -> 0 | C70: =SUMIFS(Schedule!$F$6:$F$485,Schedule!$C$6:$C$485,A70)+SUMIFS(Schedule!$H$6:$H$485,Schedule!$C$6:$C$485,A70) -> 0
