Workbook

Sheet Start Here
A1: Numbersmith - Rental Property Analyzer
A2: A friendly, formula-open workbook for evaluating a rental property purchase.
B5: HOW TO USE THIS WORKBOOK - 5 STEPS
B7: 1. | C7: Open the Deal tab. Blue cells are yours to edit: purchase price, financing terms, rent, and expenses.
B8: 2. | C8: Check the scorecard at the bottom of the Deal tab. PASS / CAUTION / FAIL updates live, using the editable Thresholds block.
B9: 3. | C9: Open 10-Year Projection to see rent growth, appreciation, loan paydown, and your IRR and equity multiple over the hold period.
B10: 4. | C10: Open Amortization for the full month-by-month schedule on the loan, driven straight from the Deal tab.
B11: 5. | C11: Use Compare to put up to four properties side by side and see which one wins on cash flow, cash-on-cash, cap rate, and DSCR.
B13: COLOR LEGEND
C14: Blue text = you type this (an input).
C15: Black text = calculated automatically. Do not overwrite - it will break the formula.
B17: WHAT'S INSIDE
B18: • Deal - single-property analyzer with cash flow, returns, and a PASS/CAUTION/FAIL scorecard.
B19: • 10-Year Projection - year-by-year rent, expenses, equity, sale proceeds, IRR, and equity multiple.
B20: • Amortization - full monthly loan schedule (principal / interest / balance).
B21: • Compare - up to 4 properties side by side, best value per row highlighted.
B22: • Charts - yearly cash flow and equity vs. loan balance, charted automatically.
B24: This tool is for planning and screening only, not tax, legal, or investment advice. Verify local numbers before you buy.
B26: Built by Numbersmith with AI assistance. Formulas are open; nothing is hidden or locked.
B28: For education and planning only, not financial advice.

Sheet Deal
A1: Deal - Single-Property Analyzer
A2: Sample: duplex, $485,000 purchase, 25% down, 6.75% / 30-yr, $3,900 combined rent.
A3: Blue = you type. Black = calculated. Edit any blue cell and everything below updates.
A5: PURCHASE & FINANCING | D5: FIXED EXPENSES | G5: MONTHLY INCOME & EXPENSE BUILD
A6: Purchase price | B6: 485000 | D6: Property tax (annual) | E6: 4200 | G6: Down payment amount | H6: =B6*B10 -> 121250
A7: Closing costs % | B7: 0.02 | D7: Insurance (annual) | E7: 1800 | G7: Loan amount | H7: =B6-H6 -> 363750
A8: Rehab budget | B8: 0 | D8: HOA (monthly) | E8: 0 | G8: Total cash needed (down + closing + rehab) | H8: =H6+B6*B7+B8 -> 130950
A9: After-repair value (ARV) | B9: 485000 | D9: Owner-paid utilities (monthly) | E9: 150 | G9: Effective gross income | H9: =B14*(1-B17)+B15 -> 3705
A10: Down payment % | B10: 0.25 | D10: GROWTH & EXIT ASSUMPTIONS | G10: Vacancy loss | H10: =B14*B17 -> 195
A11: Loan interest rate (annual) | B11: 0.0675 | D11: Annual rent growth % | E11: 0.03 | G11: Management fee | H11: =B18*H9 -> 296.4
A12: Loan term (years) | B12: 30 | D12: Annual expense growth % | E12: 0.02 | G12: Maintenance | H12: =B19*B14 -> 195
A13: INCOME | D13: Appreciation % (annual) | E13: 0.03 | G13: CapEx reserve | H13: =B20*B14 -> 195
A14: Monthly rent (combined) | B14: 3900 | D14: Selling costs % (of sale price) | E14: 0.07 | G14: Property tax (monthly) | H14: =E6/12 -> 350
A15: Other monthly income | B15: 0 | D15: Hold period (years) | E15: 10 | G15: Insurance (monthly) | H15: =E7/12 -> 150
A16: OPERATING EXPENSES (% of rent) | D16: THRESHOLDS - edit to taste | G16: HOA (monthly) | H16: =E8 -> 0
A17: Vacancy % | B17: 0.05 | D17: Min DSCR for PASS | E17: 1.25 | G17: Utilities (monthly) | H17: =E9 -> 150
A18: Management % | B18: 0.08 | D18: Min DSCR for CAUTION | E18: 1 | G18: Total operating expenses (excl. debt service) | H18: =SUM(H11:H17) -> 1336.4
A19: Maintenance % | B19: 0.05 | D19: Min cash-on-cash for PASS % | E19: 0.08 | G19: Monthly NOI | H19: =H9-H18 -> 2368.6
A20: CapEx reserve % | B20: 0.05 | D20: Min cash-on-cash for CAUTION % | E20: 0.04 | G20: Monthly P&I payment | H20: =-PMT(B11/12,B12*12,H7) -> 2359.2756
D21: Min cap rate for PASS % | E21: 0.06 | G21: Monthly cash flow | H21: =H19-H20 -> 9.3244237
D22: Min cap rate for CAUTION % | E22: 0.04 | G22: DEAL METRICS
G23: Cap rate (on purchase price) | H23: =(H19*12)/B6 -> 0.058604536
G24: Cash-on-cash return | H24: =(H21*12)/H8 -> 0.00085447182
G25: DSCR | H25: =H19/H20 -> 1.0039522
G26: 1% rule check (rent / price) | H26: =B14/B6 -> 0.0080412371
G27: 50% rule check (opex / rent) | H27: =H18/B14 -> 0.34266667
G28: Break-even occupancy | H28: =(H18+H20)/B14 -> 0.94760912
G29: Built-in equity at close (ARV - price - rehab) | H29: =B9-B6-B8 -> 0
G30: SCORECARD
G31: DSCR rating | H31: =IF(H25>=E17,"PASS",IF(H25>=E18,"CAUTION","FAIL")) -> CAUTION
G32: Cash-on-cash rating | H32: =IF(H24>=E19,"PASS",IF(H24>=E20,"CAUTION","FAIL")) -> FAIL
G33: Cap rate rating | H33: =IF(H23>=E21,"PASS",IF(H23>=E22,"CAUTION","FAIL")) -> CAUTION
G34: OVERALL | H34: =IF(OR(H31="FAIL",H32="FAIL",H33="FAIL"),"FAIL",IF(OR(H31="CAUTION",H32="CAUTION",H33="CAUTION"),"CAUTION","PASS")) -> FAIL

Sheet 10-Year Projection
A1: 10-Year Projection
A2: Rolls the Deal tab forward: rent and expense growth, loan paydown, appreciation, and the sale in the hold year.
A3: All cells here are calculated from the Deal tab. Change the Deal tab to change this projection.
A5: Metric / Year | B5: 0 | C5: =B5+1 -> 1 | D5: =C5+1 -> 2 | E5: =D5+1 -> 3 | F5: =E5+1 -> 4 | G5: =F5+1 -> 5 | H5: =G5+1 -> 6 | I5: =H5+1 -> 7 | J5: =I5+1 -> 8 | ... L5: =K5+1 -> 10
A6: Gross potential rent (annual) | C6: =Deal!$B$14*12 -> 46800 | D6: =C6*(1+Deal!$E$11) -> 48204 | E6: =D6*(1+Deal!$E$11) -> 49650.12 | F6: =E6*(1+Deal!$E$11) -> 51139.624 | G6: =F6*(1+Deal!$E$11) -> 52673.812 | H6: =G6*(1+Deal!$E$11) -> 54254.027 | I6: =H6*(1+Deal!$E$11) -> 55881.647 | J6: =I6*(1+Deal!$E$11) -> 57558.097 | K6: =J6*(1+Deal!$E$11) -> 59284.84 | L6: =K6*(1+Deal!$E$11) -> 61063.385
A7: Other income (annual) | C7: =Deal!$B$15*12 -> 0 | D7: =C7*(1+Deal!$E$11) -> 0 | E7: =D7*(1+Deal!$E$11) -> 0 | F7: =E7*(1+Deal!$E$11) -> 0 | G7: =F7*(1+Deal!$E$11) -> 0 | H7: =G7*(1+Deal!$E$11) -> 0 | I7: =H7*(1+Deal!$E$11) -> 0 | J7: =I7*(1+Deal!$E$11) -> 0 | K7: =J7*(1+Deal!$E$11) -> 0 | L7: =K7*(1+Deal!$E$11) -> 0
A8: Gross potential income | C8: =C6+C7 -> 46800 | D8: =D6+D7 -> 48204 | E8: =E6+E7 -> 49650.12 | F8: =F6+F7 -> 51139.624 | G8: =G6+G7 -> 52673.812 | H8: =H6+H7 -> 54254.027 | I8: =I6+I7 -> 55881.647 | J8: =J6+J7 -> 57558.097 | ... L8: =L6+L7 -> 61063.385
A9: Vacancy loss | C9: =C8*Deal!$B$17 -> 2340 | D9: =D8*Deal!$B$17 -> 2410.2 | E9: =E8*Deal!$B$17 -> 2482.506 | F9: =F8*Deal!$B$17 -> 2556.9812 | G9: =G8*Deal!$B$17 -> 2633.6906 | H9: =H8*Deal!$B$17 -> 2712.7013 | I9: =I8*Deal!$B$17 -> 2794.0824 | J9: =J8*Deal!$B$17 -> 2877.9048 | ... L9: =L8*Deal!$B$17 -> 3053.1693
A10: Effective gross income | C10: =C8-C9 -> 44460 | D10: =D8-D9 -> 45793.8 | E10: =E8-E9 -> 47167.614 | F10: =F8-F9 -> 48582.642 | G10: =G8-G9 -> 50040.122 | H10: =H8-H9 -> 51541.325 | I10: =I8-I9 -> 53087.565 | J10: =J8-J9 -> 54680.192 | ... L10: =L8-L9 -> 58010.216
A11: Operating expenses (excl. debt service) | C11: =Deal!$H$18*12 -> 16036.8 | D11: =C11*(1+Deal!$E$12) -> 16357.536 | E11: =D11*(1+Deal!$E$12) -> 16684.687 | F11: =E11*(1+Deal!$E$12) -> 17018.38 | G11: =F11*(1+Deal!$E$12) -> 17358.748 | H11: =G11*(1+Deal!$E$12) -> 17705.923 | I11: =H11*(1+Deal!$E$12) -> 18060.041 | J11: =I11*(1+Deal!$E$12) -> 18421.242 | K11: =J11*(1+Deal!$E$12) -> 18789.667 | L11: =K11*(1+Deal!$E$12) -> 19165.461
A12: Net operating income (NOI) | C12: =C10-C11 -> 28423.2 | D12: =D10-D11 -> 29436.264 | E12: =E10-E11 -> 30482.927 | F12: =F10-F11 -> 31564.262 | G12: =G10-G11 -> 32681.374 | H12: =H10-H11 -> 33835.402 | I12: =I10-I11 -> 35027.524 | J12: =J10-J11 -> 36258.95 | ... L12: =L10-L11 -> 38844.755
A13: Debt service (annual P&I) | C13: =Deal!$H$20*12 -> 28311.307 | D13: =Deal!$H$20*12 -> 28311.307 | E13: =Deal!$H$20*12 -> 28311.307 | F13: =Deal!$H$20*12 -> 28311.307 | G13: =Deal!$H$20*12 -> 28311.307 | H13: =Deal!$H$20*12 -> 28311.307 | I13: =Deal!$H$20*12 -> 28311.307 | J13: =Deal!$H$20*12 -> 28311.307 | ... L13: =Deal!$H$20*12 -> 28311.307
A14: Cash flow (operating) | C14: =C12-C13 -> 111.89308 | D14: =D12-D13 -> 1124.9571 | E14: =E12-E13 -> 2171.6204 | F14: =F12-F13 -> 3252.9551 | G14: =G12-G13 -> 4370.0667 | H14: =H12-H13 -> 5524.0954 | I14: =I12-I13 -> 6716.2167 | J14: =J12-J13 -> 7947.6428 | ... L14: =L12-L13 -> 10533.448
A15: Principal paydown | C15: =-CUMPRINC(Deal!$B$11/12,Deal!$B$12*12,Deal!$H$7,(C5-1)*12+1,C5*12,0) -> 3876.6585 | D15: =-CUMPRINC(Deal!$B$11/12,Deal!$B$12*12,Deal!$H$7,(D5-1)*12+1,D5*12,0) -> 4146.5823 | E15: =-CUMPRINC(Deal!$B$11/12,Deal!$B$12*12,Deal!$H$7,(E5-1)*12+1,E5*12,0) -> 4435.3003 | F15: =-CUMPRINC(Deal!$B$11/12,Deal!$B$12*12,Deal!$H$7,(F5-1)*12+1,F5*12,0) -> 4744.1211 | G15: =-CUMPRINC(Deal!$B$11/12,Deal!$B$12*12,Deal!$H$7,(G5-1)*12+1,G5*12,0) -> 5074.4444 | H15: =-CUMPRINC(Deal!$B$11/12,Deal!$B$12*12,Deal!$H$7,(H5-1)*12+1,H5*12,0) -> 5427.7675 | I15: =-CUMPRINC(Deal!$B$11/12,Deal!$B$12*12,Deal!$H$7,(I5-1)*12+1,I5*12,0) -> 5805.6918 | J15: =-CUMPRINC(Deal!$B$11/12,Deal!$B$12*12,Deal!$H$7,(J5-1)*12+1,J5*12,0) -> 6209.9301 | ... L15: =-CUMPRINC(Deal!$B$11/12,Deal!$B$12*12,Deal!$H$7,(L5-1)*12+1,L5*12,0) -> 7104.8054
A16: Loan balance (end of year) | B16: =Deal!$H$7 -> 363750 | C16: =B16-C15 -> 359873.34 | D16: =C16-D15 -> 355726.76 | E16: =D16-E15 -> 351291.46 | F16: =E16-F15 -> 346547.34 | G16: =F16-G15 -> 341472.89 | H16: =G16-H15 -> 336045.13 | I16: =H16-I15 -> 330239.43 | J16: =I16-J15 -> 324029.5 | ... L16: =K16-L15 -> 310282.38
A17: Property value | B17: =Deal!$B$6 -> 485000 | C17: =Deal!$B$6*(1+Deal!$E$13)^C5 -> 499550 | D17: =Deal!$B$6*(1+Deal!$E$13)^D5 -> 514536.5 | E17: =Deal!$B$6*(1+Deal!$E$13)^E5 -> 529972.59 | F17: =Deal!$B$6*(1+Deal!$E$13)^F5 -> 545871.77 | G17: =Deal!$B$6*(1+Deal!$E$13)^G5 -> 562247.93 | H17: =Deal!$B$6*(1+Deal!$E$13)^H5 -> 579115.36 | I17: =Deal!$B$6*(1+Deal!$E$13)^I5 -> 596488.82 | J17: =Deal!$B$6*(1+Deal!$E$13)^J5 -> 614383.49 | ... L17: =Deal!$B$6*(1+Deal!$E$13)^L5 -> 651799.44
A18: Equity (value - loan balance) | B18: =B17-B16 -> 121250 | C18: =C17-C16 -> 139676.66 | D18: =D17-D16 -> 158809.74 | E18: =E17-E16 -> 178681.14 | F18: =F17-F16 -> 199324.43 | G18: =G17-G16 -> 220775.03 | H18: =H17-H16 -> 243070.24 | I18: =I17-I16 -> 266249.39 | ... L18: =L17-L16 -> 341517.06
A19: Sale proceeds (hold year only) | C19: =IF(C5=Deal!$E$15,C17*(1-Deal!$E$14)-C16,"") | D19: =IF(D5=Deal!$E$15,D17*(1-Deal!$E$14)-D16,"") | E19: =IF(E5=Deal!$E$15,E17*(1-Deal!$E$14)-E16,"") | F19: =IF(F5=Deal!$E$15,F17*(1-Deal!$E$14)-F16,"") | G19: =IF(G5=Deal!$E$15,G17*(1-Deal!$E$14)-G16,"") | H19: =IF(H5=Deal!$E$15,H17*(1-Deal!$E$14)-H16,"") | I19: =IF(I5=Deal!$E$15,I17*(1-Deal!$E$14)-I16,"") | J19: =IF(J5=Deal!$E$15,J17*(1-Deal!$E$14)-J16,"") | ... L19: =IF(L5=Deal!$E$15,L17*(1-Deal!$E$14)-L16,"") -> 295891.1
A20: Cumulative total profit | B20: =-Deal!$H$8 -> -130950 | C20: =SUM($C$14:C14)+N(C19)-Deal!$H$8 -> -130838.11 | D20: =SUM($C$14:D14)+N(D19)-Deal!$H$8 -> -129713.15 | E20: =SUM($C$14:E14)+N(E19)-Deal!$H$8 -> -127541.53 | F20: =SUM($C$14:F14)+N(F19)-Deal!$H$8 -> -124288.57 | G20: =SUM($C$14:G14)+N(G19)-Deal!$H$8 -> -119918.51 | H20: =SUM($C$14:H14)+N(H19)-Deal!$H$8 -> -114394.41 | I20: =SUM($C$14:I14)+N(I19)-Deal!$H$8 -> -107678.2 | J20: =SUM($C$14:J14)+N(J19)-Deal!$H$8 -> -99730.553 | ... L20: =SUM($C$14:L14)+N(L19)-Deal!$H$8 -> 215913.62
A21: Net cash flow for IRR (incl. year 0 & sale) | B21: =-Deal!$H$8 -> -130950 | C21: =IF(C5<=Deal!$E$15,C14,0)+N(C19) -> 111.89308 | D21: =IF(D5<=Deal!$E$15,D14,0)+N(D19) -> 1124.9571 | E21: =IF(E5<=Deal!$E$15,E14,0)+N(E19) -> 2171.6204 | F21: =IF(F5<=Deal!$E$15,F14,0)+N(F19) -> 3252.9551 | G21: =IF(G5<=Deal!$E$15,G14,0)+N(G19) -> 4370.0667 | H21: =IF(H5<=Deal!$E$15,H14,0)+N(H19) -> 5524.0954 | I21: =IF(I5<=Deal!$E$15,I14,0)+N(I19) -> 6716.2167 | J21: =IF(J5<=Deal!$E$15,J14,0)+N(J19) -> 7947.6428 | ... L21: =IF(L5<=Deal!$E$15,L14,0)+N(L19) -> 306424.55
A23: 10-Year IRR | B23: =IRR(B21:L21) -> 0.10776986
A24: Equity multiple | B24: =SUM(C21:L21)/-B21 -> 2.6488249

Sheet Amortization
A1: Amortization - Full Monthly Schedule
A2: Driven entirely from the Deal tab: loan amount, rate, and term.
A3: Schedule covers up to 360 months (30 years). Rows past your loan term are blank.
A5: Month | B5: Beginning Balance | C5: Payment | D5: Principal | E5: Interest | F5: Ending Balance
A6: 1 | B6: =Deal!$H$7 -> 363750 | C6: =IF($A6<=Deal!$B$12*12,Deal!$H$20,"") -> 2359.2756 | D6: =IF($A6<=Deal!$B$12*12,-PPMT(Deal!$B$11/12,$A6,Deal!$B$12*12,Deal!$H$7),"") -> 313.18183 | E6: =IF($A6<=Deal!$B$12*12,-IPMT(Deal!$B$11/12,$A6,Deal!$B$12*12,Deal!$H$7),"") -> 2046.0938 | F6: =IF($A6<=Deal!$B$12*12,B6-D6,"") -> 363436.82
A7: =A6+1 -> 2 | B7: =F6 -> 363436.82 | C7: =IF($A7<=Deal!$B$12*12,Deal!$H$20,"") -> 2359.2756 | D7: =IF($A7<=Deal!$B$12*12,-PPMT(Deal!$B$11/12,$A7,Deal!$B$12*12,Deal!$H$7),"") -> 314.94347 | E7: =IF($A7<=Deal!$B$12*12,-IPMT(Deal!$B$11/12,$A7,Deal!$B$12*12,Deal!$H$7),"") -> 2044.3321 | F7: =IF($A7<=Deal!$B$12*12,B7-D7,"") -> 363121.87
A8: =A7+1 -> 3 | B8: =F7 -> 363121.87 | C8: =IF($A8<=Deal!$B$12*12,Deal!$H$20,"") -> 2359.2756 | D8: =IF($A8<=Deal!$B$12*12,-PPMT(Deal!$B$11/12,$A8,Deal!$B$12*12,Deal!$H$7),"") -> 316.71503 | E8: =IF($A8<=Deal!$B$12*12,-IPMT(Deal!$B$11/12,$A8,Deal!$B$12*12,Deal!$H$7),"") -> 2042.5605 | F8: =IF($A8<=Deal!$B$12*12,B8-D8,"") -> 362805.16
A9: =A8+1 -> 4 | B9: =F8 -> 362805.16 | C9: =IF($A9<=Deal!$B$12*12,Deal!$H$20,"") -> 2359.2756 | D9: =IF($A9<=Deal!$B$12*12,-PPMT(Deal!$B$11/12,$A9,Deal!$B$12*12,Deal!$H$7),"") -> 318.49655 | E9: =IF($A9<=Deal!$B$12*12,-IPMT(Deal!$B$11/12,$A9,Deal!$B$12*12,Deal!$H$7),"") -> 2040.779 | F9: =IF($A9<=Deal!$B$12*12,B9-D9,"") -> 362486.66
A10: =A9+1 -> 5 | B10: =F9 -> 362486.66 | C10: =IF($A10<=Deal!$B$12*12,Deal!$H$20,"") -> 2359.2756 | D10: =IF($A10<=Deal!$B$12*12,-PPMT(Deal!$B$11/12,$A10,Deal!$B$12*12,Deal!$H$7),"") -> 320.2881 | E10: =IF($A10<=Deal!$B$12*12,-IPMT(Deal!$B$11/12,$A10,Deal!$B$12*12,Deal!$H$7),"") -> 2038.9875 | F10: =IF($A10<=Deal!$B$12*12,B10-D10,"") -> 362166.38
A11: =A10+1 -> 6 | B11: =F10 -> 362166.38 | C11: =IF($A11<=Deal!$B$12*12,Deal!$H$20,"") -> 2359.2756 | D11: =IF($A11<=Deal!$B$12*12,-PPMT(Deal!$B$11/12,$A11,Deal!$B$12*12,Deal!$H$7),"") -> 322.08972 | E11: =IF($A11<=Deal!$B$12*12,-IPMT(Deal!$B$11/12,$A11,Deal!$B$12*12,Deal!$H$7),"") -> 2037.1859 | F11: =IF($A11<=Deal!$B$12*12,B11-D11,"") -> 361844.29
A12: =A11+1 -> 7 | B12: =F11 -> 361844.29 | C12: =IF($A12<=Deal!$B$12*12,Deal!$H$20,"") -> 2359.2756 | D12: =IF($A12<=Deal!$B$12*12,-PPMT(Deal!$B$11/12,$A12,Deal!$B$12*12,Deal!$H$7),"") -> 323.90147 | E12: =IF($A12<=Deal!$B$12*12,-IPMT(Deal!$B$11/12,$A12,Deal!$B$12*12,Deal!$H$7),"") -> 2035.3741 | F12: =IF($A12<=Deal!$B$12*12,B12-D12,"") -> 361520.38
A13: =A12+1 -> 8 | B13: =F12 -> 361520.38 | C13: =IF($A13<=Deal!$B$12*12,Deal!$H$20,"") -> 2359.2756 | D13: =IF($A13<=Deal!$B$12*12,-PPMT(Deal!$B$11/12,$A13,Deal!$B$12*12,Deal!$H$7),"") -> 325.72342 | E13: =IF($A13<=Deal!$B$12*12,-IPMT(Deal!$B$11/12,$A13,Deal!$B$12*12,Deal!$H$7),"") -> 2033.5522 | F13: =IF($A13<=Deal!$B$12*12,B13-D13,"") -> 361194.66
A14: =A13+1 -> 9 | B14: =F13 -> 361194.66 | C14: =IF($A14<=Deal!$B$12*12,Deal!$H$20,"") -> 2359.2756 | D14: =IF($A14<=Deal!$B$12*12,-PPMT(Deal!$B$11/12,$A14,Deal!$B$12*12,Deal!$H$7),"") -> 327.55561 | E14: =IF($A14<=Deal!$B$12*12,-IPMT(Deal!$B$11/12,$A14,Deal!$B$12*12,Deal!$H$7),"") -> 2031.72 | F14: =IF($A14<=Deal!$B$12*12,B14-D14,"") -> 360867.1
A15: =A14+1 -> 10 | B15: =F14 -> 360867.1 | C15: =IF($A15<=Deal!$B$12*12,Deal!$H$20,"") -> 2359.2756 | D15: =IF($A15<=Deal!$B$12*12,-PPMT(Deal!$B$11/12,$A15,Deal!$B$12*12,Deal!$H$7),"") -> 329.39811 | E15: =IF($A15<=Deal!$B$12*12,-IPMT(Deal!$B$11/12,$A15,Deal!$B$12*12,Deal!$H$7),"") -> 2029.8775 | F15: =IF($A15<=Deal!$B$12*12,B15-D15,"") -> 360537.71
A16: =A15+1 -> 11 | B16: =F15 -> 360537.71 | C16: =IF($A16<=Deal!$B$12*12,Deal!$H$20,"") -> 2359.2756 | D16: =IF($A16<=Deal!$B$12*12,-PPMT(Deal!$B$11/12,$A16,Deal!$B$12*12,Deal!$H$7),"") -> 331.25098 | E16: =IF($A16<=Deal!$B$12*12,-IPMT(Deal!$B$11/12,$A16,Deal!$B$12*12,Deal!$H$7),"") -> 2028.0246 | F16: =IF($A16<=Deal!$B$12*12,B16-D16,"") -> 360206.46
A17: =A16+1 -> 12 | B17: =F16 -> 360206.46 | C17: =IF($A17<=Deal!$B$12*12,Deal!$H$20,"") -> 2359.2756 | D17: =IF($A17<=Deal!$B$12*12,-PPMT(Deal!$B$11/12,$A17,Deal!$B$12*12,Deal!$H$7),"") -> 333.11426 | E17: =IF($A17<=Deal!$B$12*12,-IPMT(Deal!$B$11/12,$A17,Deal!$B$12*12,Deal!$H$7),"") -> 2026.1613 | F17: =IF($A17<=Deal!$B$12*12,B17-D17,"") -> 359873.34
A18: =A17+1 -> 13 | B18: =F17 -> 359873.34 | C18: =IF($A18<=Deal!$B$12*12,Deal!$H$20,"") -> 2359.2756 | D18: =IF($A18<=Deal!$B$12*12,-PPMT(Deal!$B$11/12,$A18,Deal!$B$12*12,Deal!$H$7),"") -> 334.98803 | E18: =IF($A18<=Deal!$B$12*12,-IPMT(Deal!$B$11/12,$A18,Deal!$B$12*12,Deal!$H$7),"") -> 2024.2875 | F18: =IF($A18<=Deal!$B$12*12,B18-D18,"") -> 359538.35
... A365: =A364+1 -> 360 | B365: =F364 -> 2346.0789 | C365: =IF($A365<=Deal!$B$12*12,Deal!$H$20,"") -> 2359.2756 | D365: =IF($A365<=Deal!$B$12*12,-PPMT(Deal!$B$11/12,$A365,Deal!$B$12*12,Deal!$H$7),"") -> 2346.0789 | E365: =IF($A365<=Deal!$B$12*12,-IPMT(Deal!$B$11/12,$A365,Deal!$B$12*12,Deal!$H$7),"") -> 13.196694 | F365: =IF($A365<=Deal!$B$12*12,B365-D365,"") -> 7.5669959e-10

Sheet Compare
A1: Compare - Up to 4 Properties
A2: Type your own numbers in each column. The best value in each result row is highlighted.
A3: Blue = you type. Black = calculated. This view uses down payment only (no closing costs) for a quick side-by-side; use the Deal tab for the full picture.
A5: Metric | B5: Property 1 - Duplex | C5: Property 2 - SFR | D5: Property 3 - Triplex | E5: Property 4 - Condo
A6: INPUTS
A7: Purchase price | B7: 485000 | C7: 350000 | D7: 620000 | E7: 275000
A8: Down payment % | B8: 0.25 | C8: 0.2 | D8: 0.25 | E8: 0.2
A9: Loan rate (annual) | B9: 0.0675 | C9: 0.065 | D9: 0.069 | E9: 0.066
A10: Loan term (years) | B10: 30 | C10: 30 | D10: 30 | E10: 30
A11: Monthly rent | B11: 3900 | C11: 2600 | D11: 5100 | E11: 2100
A12: Other monthly income | B12: 0 | C12: 0 | D12: 100 | E12: 0
A13: Vacancy % | B13: 0.05 | C13: 0.05 | D13: 0.06 | E13: 0.05
A14: Management % | B14: 0.08 | C14: 0.08 | D14: 0.08 | E14: 0.08
A15: Maintenance % | B15: 0.05 | C15: 0.05 | D15: 0.06 | E15: 0.04
A16: CapEx reserve % | B16: 0.05 | C16: 0.05 | D16: 0.05 | E16: 0.04
A17: Property tax (annual) | B17: 4200 | C17: 3200 | D17: 5400 | E17: 2600
A18: Insurance (annual) | B18: 1800 | C18: 1400 | D18: 2400 | E18: 1100
... A20: Utilities (monthly) | B20: 150 | C20: 0 | D20: 200 | E20: 0
A21: RESULTS (calculated)
A22: Loan amount | B22: =B7*(1-B8) -> 363750 | C22: =C7*(1-C8) -> 280000 | D22: =D7*(1-D8) -> 465000 | E22: =E7*(1-E8) -> 220000
A23: Down payment (cash needed) | B23: =B7*B8 -> 121250 | C23: =C7*C8 -> 70000 | D23: =D7*D8 -> 155000 | E23: =E7*E8 -> 55000
A24: Monthly P&I | B24: =-PMT(B9/12,B10*12,B22) -> 2359.2756 | C24: =-PMT(C9/12,C10*12,C22) -> 1769.7905 | D24: =-PMT(D9/12,D10*12,D22) -> 3062.4906 | E24: =-PMT(E9/12,E10*12,E22) -> 1405.0494
A25: Effective gross income (monthly) | B25: =B11*(1-B13)+B12 -> 3705 | C25: =C11*(1-C13)+C12 -> 2470 | D25: =D11*(1-D13)+D12 -> 4894 | E25: =E11*(1-E13)+E12 -> 1995
A26: Operating expenses (monthly, excl. debt) | B26: =B14*B25+B15*B11+B16*B11+B17/12+B18/12+B19+B20 -> 1336.4 | C26: =C14*C25+C15*C11+C16*C11+C17/12+C18/12+C19+C20 -> 840.93333 | D26: =D14*D25+D15*D11+D16*D11+D17/12+D18/12+D19+D20 -> 1802.52 | E26: =E14*E25+E15*E11+E16*E11+E17/12+E18/12+E19+E20 -> 885.93333
A27: Monthly NOI | B27: =B25-B26 -> 2368.6 | C27: =C25-C26 -> 1629.0667 | D27: =D25-D26 -> 3091.48 | E27: =E25-E26 -> 1109.0667
A28: Monthly cash flow | B28: =B27-B24 -> 9.3244237 | C28: =C27-C24 -> -140.7238 | D28: =D27-D24 -> 28.989383 | E28: =E27-E24 -> -295.98273
A29: Cap rate | B29: =(B27*12)/B7 -> 0.058604536 | C29: =(C27*12)/C7 -> 0.055853714 | D29: =(D27*12)/D7 -> 0.059835097 | E29: =(E27*12)/E7 -> 0.048395636
A30: Cash-on-cash return | B30: =(B28*12)/B23 -> 0.00092282957 | C30: =(C28*12)/C23 -> -0.02412408 | D30: =(D28*12)/D23 -> 0.0022443394 | E30: =(E28*12)/E23 -> -0.064578051
A31: DSCR | B31: =B27/B24 -> 1.0039522 | C31: =C27/C24 -> 0.92048562 | D31: =D27/D24 -> 1.009466 | E31: =E27/E24 -> 0.78934354

Sheet Charts
A1: Charts
A2: Built automatically from the 10-Year Projection tab. Change any Deal input and these move too.
A4: YEARLY CASH FLOW
A24: EQUITY VS. LOAN BALANCE
