Workbook

Sheet Start Here
A1: Numbersmith - Annual Budget and Net Worth Tracker
A2: A friendly, formula-open workbook for planning a household budget, tracking spending, and watching net worth grow over a year.
B5: HOW TO USE THIS WORKBOOK, 5 STEPS
B7: 1. | C7: Open Setup and enter your income sources, expense budgets by category, savings rate target, and starting cash and month.
B8: 2. | C8: Log every purchase on Transactions. Pick a category from the dropdown, and the date fills in the Month and Year helper columns on its own.
B9: 3. | C9: Open Monthly Budget to see Budget versus Actual for every category, filled in automatically from your Transactions log. A red cell means that category went over budget that month.
B10: 4. | C10: Update Net Worth once a month with your account balances: cash, savings, investments, retirement, home, vehicles, and loans. Net worth and the month-over-month change calculate on their own.
B11: 5. | C11: Use Debt Payoff to compare the avalanche and snowball payoff order, then check Dashboard for a one-page view of income versus expenses, spending by category, net worth, and savings rate.
B13: COLOR LEGEND
C15: Blue text = you type this (an input).
C16: Black text = calculated automatically. Do not overwrite it, or the formula is lost.
B18: WHAT IS INSIDE
B19: • Setup - income sources, expense budgets by grouped category, savings rate target, and starting cash and month.
B20: • Monthly Budget - Budget, Actual, and Difference for every category across all 12 months, plus income, expenses, net, savings rate, and a year-to-date column.
B21: • Transactions - a 500-row log with a category dropdown. This is the only place you type your spending; Monthly Budget reads from it automatically.
B22: • Net Worth - assets and liabilities by month, with net worth and month-over-month change calculated for you.
B23: • Debt Payoff - up to 6 debts compared under the avalanche and snowball payoff strategies, with months to payoff and total interest.
B24: • Dashboard - one page of charts: income versus expenses, spending by category, net worth over the year, and savings rate versus your target.
B26: This workbook is for personal planning only. It is not tax, legal, or investment advice.
B28: Built by Numbersmith with AI assistance. Formulas are open, nothing is hidden or locked.
B30: For education and planning only, not financial advice.

Sheet Setup
A1: Setup
A2: Type your numbers here. Every other tab reads from this one.
A4: INCOME SOURCES (up to 6)
A5: Source Name | B5: Expected Monthly Amount
A6: Primary Job Salary | B6: 6500
A7: Side Freelance Income | B7: 1300
A13: Total Monthly Income | B13: =SUM(B6:B11) -> 7800
A15: SAVINGS TARGET AND STARTING BALANCES
A16: Savings rate target (percent of income) | B16: 0.2
A17: Starting cash | B17: 8500
A18: Starting month | B18: 46023
A20: EXPENSE CATEGORIES, GROUPED (up to 25, plus Income)
A21: Category | B21: Group | C21: Monthly Budget
A22: Income | B22: Income | C22: =B13 -> 7800
A23: Rent or Mortgage | B23: Housing | C23: 1800
A24: Electric and Gas | B24: Housing | C24: 150
A25: Internet and Phone | B25: Housing | C25: 90
A26: Car Payment | B26: Transport | C26: 350
A27: Fuel | B27: Transport | C27: 160
A28: Public Transit and Rideshare | B28: Transport | C28: 60
A29: Groceries | B29: Food | C29: 650
A30: Dining Out | B30: Food | C30: 220
A31: Health Insurance | B31: Insurance | C31: 340
A32: Auto Insurance | B32: Insurance | C32: 120
A33: Life Insurance | B33: Insurance | C33: 45
A34: Credit Card Payment | B34: Debt | C34: 150
... A44: Miscellaneous | B44: Other | C44: 80
A49: Total Monthly Expense Budget | C49: =SUM(C23:C47) -> 5895
A51: Sample data describes a fictional household earning about $7,800 a month. Replace every blue cell with your own numbers.

Sheet Transactions
A1: Transactions
A2: Log every purchase and deposit here. Category comes from a dropdown; Month and Year fill in on their own. Monthly Budget reads Actual figures straight from this log.
A4: Date | B4: Description | C4: Category | D4: Amount | E4: Notes | F4: Month (auto) | G4: Year (auto)
A5: 46023 | B5: Primary job paycheck | C5: Income | D5: 6500 | E5: Direct deposit | F5: =IF($A5="","",MONTH($A5)) -> 1 | G5: =IF($A5="","",YEAR($A5)) -> 2026
A6: 46023 | B6: Rent payment | C6: Rent or Mortgage | D6: 1800 | E6: Autopay | F6: =IF($A6="","",MONTH($A6)) -> 1 | G6: =IF($A6="","",YEAR($A6)) -> 2026
A7: 46024 | B7: 401k contribution | C7: Retirement 401k or IRA | D7: 500 | E7: Payroll deferral | F7: =IF($A7="","",MONTH($A7)) -> 1 | G7: =IF($A7="","",YEAR($A7)) -> 2026
A8: 46025 | B8: Health insurance premium | C8: Health Insurance | D8: 340 | E8: Payroll deduction | F8: =IF($A8="","",MONTH($A8)) -> 1 | G8: =IF($A8="","",YEAR($A8)) -> 2026
A9: 46026 | B9: Transfer to emergency savings | C9: Emergency Fund | D9: 200 | E9: Automatic transfer | F9: =IF($A9="","",MONTH($A9)) -> 1 | G9: =IF($A9="","",YEAR($A9)) -> 2026
A10: 46027 | B10: Auto loan payment | C10: Car Payment | D10: 350 | E10: Autopay | F10: =IF($A10="","",MONTH($A10)) -> 1 | G10: =IF($A10="","",YEAR($A10)) -> 2026
A11: 46028 | B11: Internet and phone bill | C11: Internet and Phone | D11: 89 | E11: Autopay | F11: =IF($A11="","",MONTH($A11)) -> 1 | G11: =IF($A11="","",YEAR($A11)) -> 2026
A12: 46030 | B12: Electric and gas bill | C12: Electric and Gas | D12: 145 | E12: Autopay | F12: =IF($A12="","",MONTH($A12)) -> 1 | G12: =IF($A12="","",YEAR($A12)) -> 2026
A13: 46031 | B13: Streaming and software subscriptions | C13: Subscriptions | D13: 58 | E13: Debit card | F13: =IF($A13="","",MONTH($A13)) -> 1 | G13: =IF($A13="","",YEAR($A13)) -> 2026
A14: 46032 | B14: Grocery shopping | C14: Groceries | D14: 315 | E14: Debit card | F14: =IF($A14="","",MONTH($A14)) -> 1 | G14: =IF($A14="","",YEAR($A14)) -> 2026
A15: 46034 | B15: Student loan payment | C15: Student Loan Payment | D15: 220 | E15: Autopay | F15: =IF($A15="","",MONTH($A15)) -> 1 | G15: =IF($A15="","",YEAR($A15)) -> 2026
A16: 46036 | B16: Gas station fill-up | C16: Fuel | D16: 85 | E16: Debit card | F16: =IF($A16="","",MONTH($A16)) -> 1 | G16: =IF($A16="","",YEAR($A16)) -> 2026
... A51: 46109 | B51: Brokerage account transfer | C51: Brokerage Investing | D51: 300 | E51: Automatic transfer | F51: =IF($A51="","",MONTH($A51)) -> 3 | G51: =IF($A51="","",YEAR($A51)) -> 2026
F52: =IF($A52="","",MONTH($A52)) | G52: =IF($A52="","",YEAR($A52))
F53: =IF($A53="","",MONTH($A53)) | G53: =IF($A53="","",YEAR($A53))
F54: =IF($A54="","",MONTH($A54)) | G54: =IF($A54="","",YEAR($A54))
F55: =IF($A55="","",MONTH($A55)) | G55: =IF($A55="","",YEAR($A55))
F56: =IF($A56="","",MONTH($A56)) | G56: =IF($A56="","",YEAR($A56))
F57: =IF($A57="","",MONTH($A57)) | G57: =IF($A57="","",YEAR($A57))
F58: =IF($A58="","",MONTH($A58)) | G58: =IF($A58="","",YEAR($A58))
F59: =IF($A59="","",MONTH($A59)) | G59: =IF($A59="","",YEAR($A59))
F60: =IF($A60="","",MONTH($A60)) | G60: =IF($A60="","",YEAR($A60))
F61: =IF($A61="","",MONTH($A61)) | G61: =IF($A61="","",YEAR($A61))
F62: =IF($A62="","",MONTH($A62)) | G62: =IF($A62="","",YEAR($A62))
F63: =IF($A63="","",MONTH($A63)) | G63: =IF($A63="","",YEAR($A63))
... F504: =IF($A504="","",MONTH($A504)) | G504: =IF($A504="","",YEAR($A504))

Sheet Monthly Budget
A1: Monthly Budget
A2: Budget pulls straight from Setup. Actual pulls straight from Transactions. Nothing on this tab needs to be typed.
A4: Category | B4: Line | C4: Jan | D4: Feb | E4: Mar | F4: Apr | G4: May | H4: Jun | I4: Jul | J4: Aug | K4: Sep | L4: Oct | M4: Nov | N4: Dec | O4: YTD
A5: =Setup!A22 -> Income | B5: Budget | C5: =Setup!C22 -> 7800 | D5: =Setup!C22 -> 7800 | E5: =Setup!C22 -> 7800 | F5: =Setup!C22 -> 7800 | G5: =Setup!C22 -> 7800 | H5: =Setup!C22 -> 7800 | I5: =Setup!C22 -> 7800 | J5: =Setup!C22 -> 7800 | K5: =Setup!C22 -> 7800 | L5: =Setup!C22 -> 7800 | M5: =Setup!C22 -> 7800 | N5: =Setup!C22 -> 7800 | O5: =SUM(C5:N5) -> 93600
B6: Actual | C6: =SUMIFS(Transactions!$D$5:$D$504,Transactions!$C$5:$C$504,$A5,Transactions!$F$5:$F$504,1,Transactions!$G$5:$G$504,YEAR(Setup!$B$18)) -> 7800 | D6: =SUMIFS(Transactions!$D$5:$D$504,Transactions!$C$5:$C$504,$A5,Transactions!$F$5:$F$504,2,Transactions!$G$5:$G$504,YEAR(Setup!$B$18)) -> 7950 | E6: =SUMIFS(Transactions!$D$5:$D$504,Transactions!$C$5:$C$504,$A5,Transactions!$F$5:$F$504,3,Transactions!$G$5:$G$504,YEAR(Setup!$B$18)) -> 7600 | F6: =SUMIFS(Transactions!$D$5:$D$504,Transactions!$C$5:$C$504,$A5,Transactions!$F$5:$F$504,4,Transactions!$G$5:$G$504,YEAR(Setup!$B$18)) -> 0 | G6: =SUMIFS(Transactions!$D$5:$D$504,Transactions!$C$5:$C$504,$A5,Transactions!$F$5:$F$504,5,Transactions!$G$5:$G$504,YEAR(Setup!$B$18)) -> 0 | H6: =SUMIFS(Transactions!$D$5:$D$504,Transactions!$C$5:$C$504,$A5,Transactions!$F$5:$F$504,6,Transactions!$G$5:$G$504,YEAR(Setup!$B$18)) -> 0 | I6: =SUMIFS(Transactions!$D$5:$D$504,Transactions!$C$5:$C$504,$A5,Transactions!$F$5:$F$504,7,Transactions!$G$5:$G$504,YEAR(Setup!$B$18)) -> 0 | J6: =SUMIFS(Transactions!$D$5:$D$504,Transactions!$C$5:$C$504,$A5,Transactions!$F$5:$F$504,8,Transactions!$G$5:$G$504,YEAR(Setup!$B$18)) -> 0 | K6: =SUMIFS(Transactions!$D$5:$D$504,Transactions!$C$5:$C$504,$A5,Transactions!$F$5:$F$504,9,Transactions!$G$5:$G$504,YEAR(Setup!$B$18)) -> 0 | L6: =SUMIFS(Transactions!$D$5:$D$504,Transactions!$C$5:$C$504,$A5,Transactions!$F$5:$F$504,10,Transactions!$G$5:$G$504,YEAR(Setup!$B$18)) -> 0 | M6: =SUMIFS(Transactions!$D$5:$D$504,Transactions!$C$5:$C$504,$A5,Transactions!$F$5:$F$504,11,Transactions!$G$5:$G$504,YEAR(Setup!$B$18)) -> 0 | N6: =SUMIFS(Transactions!$D$5:$D$504,Transactions!$C$5:$C$504,$A5,Transactions!$F$5:$F$504,12,Transactions!$G$5:$G$504,YEAR(Setup!$B$18)) -> 0 | O6: =SUM(C6:N6) -> 23350
B7: Difference | C7: =C6-C5 -> 0 | D7: =D6-D5 -> 150 | E7: =E6-E5 -> -200 | F7: =F6-F5 -> -7800 | G7: =G6-G5 -> -7800 | H7: =H6-H5 -> -7800 | I7: =I6-I5 -> -7800 | J7: =J6-J5 -> -7800 | ... O7: =O6-O5 -> -70250
A9: HOUSING
A10: =Setup!A23 -> Rent or Mortgage | B10: Budget | C10: =Setup!C23 -> 1800 | D10: =Setup!C23 -> 1800 | E10: =Setup!C23 -> 1800 | F10: =Setup!C23 -> 1800 | G10: =Setup!C23 -> 1800 | H10: =Setup!C23 -> 1800 | I10: =Setup!C23 -> 1800 | J10: =Setup!C23 -> 1800 | K10: =Setup!C23 -> 1800 | L10: =Setup!C23 -> 1800 | M10: =Setup!C23 -> 1800 | N10: =Setup!C23 -> 1800 | O10: =SUM(C10:N10) -> 21600
B11: Actual | C11: =SUMIFS(Transactions!$D$5:$D$504,Transactions!$C$5:$C$504,$A10,Transactions!$F$5:$F$504,1,Transactions!$G$5:$G$504,YEAR(Setup!$B$18)) -> 1800 | D11: =SUMIFS(Transactions!$D$5:$D$504,Transactions!$C$5:$C$504,$A10,Transactions!$F$5:$F$504,2,Transactions!$G$5:$G$504,YEAR(Setup!$B$18)) -> 1800 | E11: =SUMIFS(Transactions!$D$5:$D$504,Transactions!$C$5:$C$504,$A10,Transactions!$F$5:$F$504,3,Transactions!$G$5:$G$504,YEAR(Setup!$B$18)) -> 1800 | F11: =SUMIFS(Transactions!$D$5:$D$504,Transactions!$C$5:$C$504,$A10,Transactions!$F$5:$F$504,4,Transactions!$G$5:$G$504,YEAR(Setup!$B$18)) -> 0 | G11: =SUMIFS(Transactions!$D$5:$D$504,Transactions!$C$5:$C$504,$A10,Transactions!$F$5:$F$504,5,Transactions!$G$5:$G$504,YEAR(Setup!$B$18)) -> 0 | H11: =SUMIFS(Transactions!$D$5:$D$504,Transactions!$C$5:$C$504,$A10,Transactions!$F$5:$F$504,6,Transactions!$G$5:$G$504,YEAR(Setup!$B$18)) -> 0 | I11: =SUMIFS(Transactions!$D$5:$D$504,Transactions!$C$5:$C$504,$A10,Transactions!$F$5:$F$504,7,Transactions!$G$5:$G$504,YEAR(Setup!$B$18)) -> 0 | J11: =SUMIFS(Transactions!$D$5:$D$504,Transactions!$C$5:$C$504,$A10,Transactions!$F$5:$F$504,8,Transactions!$G$5:$G$504,YEAR(Setup!$B$18)) -> 0 | K11: =SUMIFS(Transactions!$D$5:$D$504,Transactions!$C$5:$C$504,$A10,Transactions!$F$5:$F$504,9,Transactions!$G$5:$G$504,YEAR(Setup!$B$18)) -> 0 | L11: =SUMIFS(Transactions!$D$5:$D$504,Transactions!$C$5:$C$504,$A10,Transactions!$F$5:$F$504,10,Transactions!$G$5:$G$504,YEAR(Setup!$B$18)) -> 0 | M11: =SUMIFS(Transactions!$D$5:$D$504,Transactions!$C$5:$C$504,$A10,Transactions!$F$5:$F$504,11,Transactions!$G$5:$G$504,YEAR(Setup!$B$18)) -> 0 | N11: =SUMIFS(Transactions!$D$5:$D$504,Transactions!$C$5:$C$504,$A10,Transactions!$F$5:$F$504,12,Transactions!$G$5:$G$504,YEAR(Setup!$B$18)) -> 0 | O11: =SUM(C11:N11) -> 5400
B12: Difference | C12: =C11-C10 -> 0 | D12: =D11-D10 -> 0 | E12: =E11-E10 -> 0 | F12: =F11-F10 -> -1800 | G12: =G11-G10 -> -1800 | H12: =H11-H10 -> -1800 | I12: =I11-I10 -> -1800 | J12: =J11-J10 -> -1800 | ... O12: =O11-O10 -> -16200
A13: =Setup!A24 -> Electric and Gas | B13: Budget | C13: =Setup!C24 -> 150 | D13: =Setup!C24 -> 150 | E13: =Setup!C24 -> 150 | F13: =Setup!C24 -> 150 | G13: =Setup!C24 -> 150 | H13: =Setup!C24 -> 150 | I13: =Setup!C24 -> 150 | J13: =Setup!C24 -> 150 | K13: =Setup!C24 -> 150 | L13: =Setup!C24 -> 150 | M13: =Setup!C24 -> 150 | N13: =Setup!C24 -> 150 | O13: =SUM(C13:N13) -> 1800
B14: Actual | C14: =SUMIFS(Transactions!$D$5:$D$504,Transactions!$C$5:$C$504,$A13,Transactions!$F$5:$F$504,1,Transactions!$G$5:$G$504,YEAR(Setup!$B$18)) -> 145 | D14: =SUMIFS(Transactions!$D$5:$D$504,Transactions!$C$5:$C$504,$A13,Transactions!$F$5:$F$504,2,Transactions!$G$5:$G$504,YEAR(Setup!$B$18)) -> 162 | E14: =SUMIFS(Transactions!$D$5:$D$504,Transactions!$C$5:$C$504,$A13,Transactions!$F$5:$F$504,3,Transactions!$G$5:$G$504,YEAR(Setup!$B$18)) -> 138 | F14: =SUMIFS(Transactions!$D$5:$D$504,Transactions!$C$5:$C$504,$A13,Transactions!$F$5:$F$504,4,Transactions!$G$5:$G$504,YEAR(Setup!$B$18)) -> 0 | G14: =SUMIFS(Transactions!$D$5:$D$504,Transactions!$C$5:$C$504,$A13,Transactions!$F$5:$F$504,5,Transactions!$G$5:$G$504,YEAR(Setup!$B$18)) -> 0 | H14: =SUMIFS(Transactions!$D$5:$D$504,Transactions!$C$5:$C$504,$A13,Transactions!$F$5:$F$504,6,Transactions!$G$5:$G$504,YEAR(Setup!$B$18)) -> 0 | I14: =SUMIFS(Transactions!$D$5:$D$504,Transactions!$C$5:$C$504,$A13,Transactions!$F$5:$F$504,7,Transactions!$G$5:$G$504,YEAR(Setup!$B$18)) -> 0 | J14: =SUMIFS(Transactions!$D$5:$D$504,Transactions!$C$5:$C$504,$A13,Transactions!$F$5:$F$504,8,Transactions!$G$5:$G$504,YEAR(Setup!$B$18)) -> 0 | K14: =SUMIFS(Transactions!$D$5:$D$504,Transactions!$C$5:$C$504,$A13,Transactions!$F$5:$F$504,9,Transactions!$G$5:$G$504,YEAR(Setup!$B$18)) -> 0 | L14: =SUMIFS(Transactions!$D$5:$D$504,Transactions!$C$5:$C$504,$A13,Transactions!$F$5:$F$504,10,Transactions!$G$5:$G$504,YEAR(Setup!$B$18)) -> 0 | M14: =SUMIFS(Transactions!$D$5:$D$504,Transactions!$C$5:$C$504,$A13,Transactions!$F$5:$F$504,11,Transactions!$G$5:$G$504,YEAR(Setup!$B$18)) -> 0 | N14: =SUMIFS(Transactions!$D$5:$D$504,Transactions!$C$5:$C$504,$A13,Transactions!$F$5:$F$504,12,Transactions!$G$5:$G$504,YEAR(Setup!$B$18)) -> 0 | O14: =SUM(C14:N14) -> 445
B15: Difference | C15: =C14-C13 -> -5 | D15: =D14-D13 -> 12 | E15: =E14-E13 -> -12 | F15: =F14-F13 -> -150 | G15: =G14-G13 -> -150 | H15: =H14-H13 -> -150 | I15: =I14-I13 -> -150 | J15: =J14-J13 -> -150 | ... O15: =O14-O13 -> -1355
A16: =Setup!A25 -> Internet and Phone | B16: Budget | C16: =Setup!C25 -> 90 | D16: =Setup!C25 -> 90 | E16: =Setup!C25 -> 90 | F16: =Setup!C25 -> 90 | G16: =Setup!C25 -> 90 | H16: =Setup!C25 -> 90 | I16: =Setup!C25 -> 90 | J16: =Setup!C25 -> 90 | K16: =Setup!C25 -> 90 | L16: =Setup!C25 -> 90 | M16: =Setup!C25 -> 90 | N16: =Setup!C25 -> 90 | O16: =SUM(C16:N16) -> 1080
B17: Actual | C17: =SUMIFS(Transactions!$D$5:$D$504,Transactions!$C$5:$C$504,$A16,Transactions!$F$5:$F$504,1,Transactions!$G$5:$G$504,YEAR(Setup!$B$18)) -> 89 | D17: =SUMIFS(Transactions!$D$5:$D$504,Transactions!$C$5:$C$504,$A16,Transactions!$F$5:$F$504,2,Transactions!$G$5:$G$504,YEAR(Setup!$B$18)) -> 0 | E17: =SUMIFS(Transactions!$D$5:$D$504,Transactions!$C$5:$C$504,$A16,Transactions!$F$5:$F$504,3,Transactions!$G$5:$G$504,YEAR(Setup!$B$18)) -> 95 | F17: =SUMIFS(Transactions!$D$5:$D$504,Transactions!$C$5:$C$504,$A16,Transactions!$F$5:$F$504,4,Transactions!$G$5:$G$504,YEAR(Setup!$B$18)) -> 0 | G17: =SUMIFS(Transactions!$D$5:$D$504,Transactions!$C$5:$C$504,$A16,Transactions!$F$5:$F$504,5,Transactions!$G$5:$G$504,YEAR(Setup!$B$18)) -> 0 | H17: =SUMIFS(Transactions!$D$5:$D$504,Transactions!$C$5:$C$504,$A16,Transactions!$F$5:$F$504,6,Transactions!$G$5:$G$504,YEAR(Setup!$B$18)) -> 0 | I17: =SUMIFS(Transactions!$D$5:$D$504,Transactions!$C$5:$C$504,$A16,Transactions!$F$5:$F$504,7,Transactions!$G$5:$G$504,YEAR(Setup!$B$18)) -> 0 | J17: =SUMIFS(Transactions!$D$5:$D$504,Transactions!$C$5:$C$504,$A16,Transactions!$F$5:$F$504,8,Transactions!$G$5:$G$504,YEAR(Setup!$B$18)) -> 0 | K17: =SUMIFS(Transactions!$D$5:$D$504,Transactions!$C$5:$C$504,$A16,Transactions!$F$5:$F$504,9,Transactions!$G$5:$G$504,YEAR(Setup!$B$18)) -> 0 | L17: =SUMIFS(Transactions!$D$5:$D$504,Transactions!$C$5:$C$504,$A16,Transactions!$F$5:$F$504,10,Transactions!$G$5:$G$504,YEAR(Setup!$B$18)) -> 0 | M17: =SUMIFS(Transactions!$D$5:$D$504,Transactions!$C$5:$C$504,$A16,Transactions!$F$5:$F$504,11,Transactions!$G$5:$G$504,YEAR(Setup!$B$18)) -> 0 | N17: =SUMIFS(Transactions!$D$5:$D$504,Transactions!$C$5:$C$504,$A16,Transactions!$F$5:$F$504,12,Transactions!$G$5:$G$504,YEAR(Setup!$B$18)) -> 0 | O17: =SUM(C17:N17) -> 184
B18: Difference | C18: =C17-C16 -> -1 | D18: =D17-D16 -> -90 | E18: =E17-E16 -> 5 | F18: =F17-F16 -> -90 | G18: =G17-G16 -> -90 | H18: =H17-H16 -> -90 | I18: =I17-I16 -> -90 | J18: =J17-J16 -> -90 | ... O18: =O17-O16 -> -896
A19: Housing Total | B19: Budget | C19: =C10+C13+C16 -> 2040 | D19: =D10+D13+D16 -> 2040 | E19: =E10+E13+E16 -> 2040 | F19: =F10+F13+F16 -> 2040 | G19: =G10+G13+G16 -> 2040 | H19: =H10+H13+H16 -> 2040 | I19: =I10+I13+I16 -> 2040 | J19: =J10+J13+J16 -> 2040 | ... N19: =N10+N13+N16 -> 2040 | O19: =SUM(C19:N19) -> 24480
B20: Actual | C20: =C11+C14+C17 -> 2034 | D20: =D11+D14+D17 -> 1962 | E20: =E11+E14+E17 -> 2033 | F20: =F11+F14+F17 -> 0 | G20: =G11+G14+G17 -> 0 | H20: =H11+H14+H17 -> 0 | I20: =I11+I14+I17 -> 0 | J20: =J11+J14+J17 -> 0 | ... N20: =N11+N14+N17 -> 0 | O20: =SUM(C20:N20) -> 6029
B21: Difference | C21: =C20-C19 -> -6 | D21: =D20-D19 -> -78 | E21: =E20-E19 -> -7 | F21: =F20-F19 -> -2040 | G21: =G20-G19 -> -2040 | H21: =H20-H19 -> -2040 | I21: =I20-I19 -> -2040 | J21: =J20-J19 -> -2040 | ... O21: =O20-O19 -> -18451
A23: TRANSPORT
A24: =Setup!A26 -> Car Payment | B24: Budget | C24: =Setup!C26 -> 350 | D24: =Setup!C26 -> 350 | E24: =Setup!C26 -> 350 | F24: =Setup!C26 -> 350 | G24: =Setup!C26 -> 350 | H24: =Setup!C26 -> 350 | I24: =Setup!C26 -> 350 | J24: =Setup!C26 -> 350 | K24: =Setup!C26 -> 350 | L24: =Setup!C26 -> 350 | M24: =Setup!C26 -> 350 | N24: =Setup!C26 -> 350 | O24: =SUM(C24:N24) -> 4200
B25: Actual | C25: =SUMIFS(Transactions!$D$5:$D$504,Transactions!$C$5:$C$504,$A24,Transactions!$F$5:$F$504,1,Transactions!$G$5:$G$504,YEAR(Setup!$B$18)) -> 350 | D25: =SUMIFS(Transactions!$D$5:$D$504,Transactions!$C$5:$C$504,$A24,Transactions!$F$5:$F$504,2,Transactions!$G$5:$G$504,YEAR(Setup!$B$18)) -> 350 | E25: =SUMIFS(Transactions!$D$5:$D$504,Transactions!$C$5:$C$504,$A24,Transactions!$F$5:$F$504,3,Transactions!$G$5:$G$504,YEAR(Setup!$B$18)) -> 350 | F25: =SUMIFS(Transactions!$D$5:$D$504,Transactions!$C$5:$C$504,$A24,Transactions!$F$5:$F$504,4,Transactions!$G$5:$G$504,YEAR(Setup!$B$18)) -> 0 | G25: =SUMIFS(Transactions!$D$5:$D$504,Transactions!$C$5:$C$504,$A24,Transactions!$F$5:$F$504,5,Transactions!$G$5:$G$504,YEAR(Setup!$B$18)) -> 0 | H25: =SUMIFS(Transactions!$D$5:$D$504,Transactions!$C$5:$C$504,$A24,Transactions!$F$5:$F$504,6,Transactions!$G$5:$G$504,YEAR(Setup!$B$18)) -> 0 | I25: =SUMIFS(Transactions!$D$5:$D$504,Transactions!$C$5:$C$504,$A24,Transactions!$F$5:$F$504,7,Transactions!$G$5:$G$504,YEAR(Setup!$B$18)) -> 0 | J25: =SUMIFS(Transactions!$D$5:$D$504,Transactions!$C$5:$C$504,$A24,Transactions!$F$5:$F$504,8,Transactions!$G$5:$G$504,YEAR(Setup!$B$18)) -> 0 | K25: =SUMIFS(Transactions!$D$5:$D$504,Transactions!$C$5:$C$504,$A24,Transactions!$F$5:$F$504,9,Transactions!$G$5:$G$504,YEAR(Setup!$B$18)) -> 0 | L25: =SUMIFS(Transactions!$D$5:$D$504,Transactions!$C$5:$C$504,$A24,Transactions!$F$5:$F$504,10,Transactions!$G$5:$G$504,YEAR(Setup!$B$18)) -> 0 | M25: =SUMIFS(Transactions!$D$5:$D$504,Transactions!$C$5:$C$504,$A24,Transactions!$F$5:$F$504,11,Transactions!$G$5:$G$504,YEAR(Setup!$B$18)) -> 0 | N25: =SUMIFS(Transactions!$D$5:$D$504,Transactions!$C$5:$C$504,$A24,Transactions!$F$5:$F$504,12,Transactions!$G$5:$G$504,YEAR(Setup!$B$18)) -> 0 | O25: =SUM(C25:N25) -> 1050
B26: Difference | C26: =C25-C24 -> 0 | D26: =D25-D24 -> 0 | E26: =E25-E24 -> 0 | F26: =F25-F24 -> -350 | G26: =G25-G24 -> -350 | H26: =H25-H24 -> -350 | I26: =I25-I24 -> -350 | J26: =J25-J24 -> -350 | ... O26: =O25-O24 -> -3150
A27: =Setup!A27 -> Fuel | B27: Budget | C27: =Setup!C27 -> 160 | D27: =Setup!C27 -> 160 | E27: =Setup!C27 -> 160 | F27: =Setup!C27 -> 160 | G27: =Setup!C27 -> 160 | H27: =Setup!C27 -> 160 | I27: =Setup!C27 -> 160 | J27: =Setup!C27 -> 160 | K27: =Setup!C27 -> 160 | L27: =Setup!C27 -> 160 | M27: =Setup!C27 -> 160 | N27: =Setup!C27 -> 160 | O27: =SUM(C27:N27) -> 1920
B28: Actual | C28: =SUMIFS(Transactions!$D$5:$D$504,Transactions!$C$5:$C$504,$A27,Transactions!$F$5:$F$504,1,Transactions!$G$5:$G$504,YEAR(Setup!$B$18)) -> 85 | D28: =SUMIFS(Transactions!$D$5:$D$504,Transactions!$C$5:$C$504,$A27,Transactions!$F$5:$F$504,2,Transactions!$G$5:$G$504,YEAR(Setup!$B$18)) -> 98 | E28: =SUMIFS(Transactions!$D$5:$D$504,Transactions!$C$5:$C$504,$A27,Transactions!$F$5:$F$504,3,Transactions!$G$5:$G$504,YEAR(Setup!$B$18)) -> 0 | F28: =SUMIFS(Transactions!$D$5:$D$504,Transactions!$C$5:$C$504,$A27,Transactions!$F$5:$F$504,4,Transactions!$G$5:$G$504,YEAR(Setup!$B$18)) -> 0 | G28: =SUMIFS(Transactions!$D$5:$D$504,Transactions!$C$5:$C$504,$A27,Transactions!$F$5:$F$504,5,Transactions!$G$5:$G$504,YEAR(Setup!$B$18)) -> 0 | H28: =SUMIFS(Transactions!$D$5:$D$504,Transactions!$C$5:$C$504,$A27,Transactions!$F$5:$F$504,6,Transactions!$G$5:$G$504,YEAR(Setup!$B$18)) -> 0 | I28: =SUMIFS(Transactions!$D$5:$D$504,Transactions!$C$5:$C$504,$A27,Transactions!$F$5:$F$504,7,Transactions!$G$5:$G$504,YEAR(Setup!$B$18)) -> 0 | J28: =SUMIFS(Transactions!$D$5:$D$504,Transactions!$C$5:$C$504,$A27,Transactions!$F$5:$F$504,8,Transactions!$G$5:$G$504,YEAR(Setup!$B$18)) -> 0 | K28: =SUMIFS(Transactions!$D$5:$D$504,Transactions!$C$5:$C$504,$A27,Transactions!$F$5:$F$504,9,Transactions!$G$5:$G$504,YEAR(Setup!$B$18)) -> 0 | L28: =SUMIFS(Transactions!$D$5:$D$504,Transactions!$C$5:$C$504,$A27,Transactions!$F$5:$F$504,10,Transactions!$G$5:$G$504,YEAR(Setup!$B$18)) -> 0 | M28: =SUMIFS(Transactions!$D$5:$D$504,Transactions!$C$5:$C$504,$A27,Transactions!$F$5:$F$504,11,Transactions!$G$5:$G$504,YEAR(Setup!$B$18)) -> 0 | N28: =SUMIFS(Transactions!$D$5:$D$504,Transactions!$C$5:$C$504,$A27,Transactions!$F$5:$F$504,12,Transactions!$G$5:$G$504,YEAR(Setup!$B$18)) -> 0 | O28: =SUM(C28:N28) -> 183
B29: Difference | C29: =C28-C27 -> -75 | D29: =D28-D27 -> -62 | E29: =E28-E27 -> -160 | F29: =F28-F27 -> -160 | G29: =G28-G27 -> -160 | H29: =H28-H27 -> -160 | I29: =I28-I27 -> -160 | J29: =J28-J27 -> -160 | ... O29: =O28-O27 -> -1737
A30: =Setup!A28 -> Public Transit and Rideshare | B30: Budget | C30: =Setup!C28 -> 60 | D30: =Setup!C28 -> 60 | E30: =Setup!C28 -> 60 | F30: =Setup!C28 -> 60 | G30: =Setup!C28 -> 60 | H30: =Setup!C28 -> 60 | I30: =Setup!C28 -> 60 | J30: =Setup!C28 -> 60 | K30: =Setup!C28 -> 60 | L30: =Setup!C28 -> 60 | M30: =Setup!C28 -> 60 | N30: =Setup!C28 -> 60 | O30: =SUM(C30:N30) -> 720
B31: Actual | C31: =SUMIFS(Transactions!$D$5:$D$504,Transactions!$C$5:$C$504,$A30,Transactions!$F$5:$F$504,1,Transactions!$G$5:$G$504,YEAR(Setup!$B$18)) -> 0 | D31: =SUMIFS(Transactions!$D$5:$D$504,Transactions!$C$5:$C$504,$A30,Transactions!$F$5:$F$504,2,Transactions!$G$5:$G$504,YEAR(Setup!$B$18)) -> 60 | E31: =SUMIFS(Transactions!$D$5:$D$504,Transactions!$C$5:$C$504,$A30,Transactions!$F$5:$F$504,3,Transactions!$G$5:$G$504,YEAR(Setup!$B$18)) -> 0 | F31: =SUMIFS(Transactions!$D$5:$D$504,Transactions!$C$5:$C$504,$A30,Transactions!$F$5:$F$504,4,Transactions!$G$5:$G$504,YEAR(Setup!$B$18)) -> 0 | G31: =SUMIFS(Transactions!$D$5:$D$504,Transactions!$C$5:$C$504,$A30,Transactions!$F$5:$F$504,5,Transactions!$G$5:$G$504,YEAR(Setup!$B$18)) -> 0 | H31: =SUMIFS(Transactions!$D$5:$D$504,Transactions!$C$5:$C$504,$A30,Transactions!$F$5:$F$504,6,Transactions!$G$5:$G$504,YEAR(Setup!$B$18)) -> 0 | I31: =SUMIFS(Transactions!$D$5:$D$504,Transactions!$C$5:$C$504,$A30,Transactions!$F$5:$F$504,7,Transactions!$G$5:$G$504,YEAR(Setup!$B$18)) -> 0 | J31: =SUMIFS(Transactions!$D$5:$D$504,Transactions!$C$5:$C$504,$A30,Transactions!$F$5:$F$504,8,Transactions!$G$5:$G$504,YEAR(Setup!$B$18)) -> 0 | K31: =SUMIFS(Transactions!$D$5:$D$504,Transactions!$C$5:$C$504,$A30,Transactions!$F$5:$F$504,9,Transactions!$G$5:$G$504,YEAR(Setup!$B$18)) -> 0 | L31: =SUMIFS(Transactions!$D$5:$D$504,Transactions!$C$5:$C$504,$A30,Transactions!$F$5:$F$504,10,Transactions!$G$5:$G$504,YEAR(Setup!$B$18)) -> 0 | M31: =SUMIFS(Transactions!$D$5:$D$504,Transactions!$C$5:$C$504,$A30,Transactions!$F$5:$F$504,11,Transactions!$G$5:$G$504,YEAR(Setup!$B$18)) -> 0 | N31: =SUMIFS(Transactions!$D$5:$D$504,Transactions!$C$5:$C$504,$A30,Transactions!$F$5:$F$504,12,Transactions!$G$5:$G$504,YEAR(Setup!$B$18)) -> 0 | O31: =SUM(C31:N31) -> 60
B32: Difference | C32: =C31-C30 -> -60 | D32: =D31-D30 -> 0 | E32: =E31-E30 -> -60 | F32: =F31-F30 -> -60 | G32: =G31-G30 -> -60 | H32: =H31-H30 -> -60 | I32: =I31-I30 -> -60 | J32: =J31-J30 -> -60 | ... O32: =O31-O30 -> -660
A33: Transport Total | B33: Budget | C33: =C24+C27+C30 -> 570 | D33: =D24+D27+D30 -> 570 | E33: =E24+E27+E30 -> 570 | F33: =F24+F27+F30 -> 570 | G33: =G24+G27+G30 -> 570 | H33: =H24+H27+H30 -> 570 | I33: =I24+I27+I30 -> 570 | J33: =J24+J27+J30 -> 570 | ... N33: =N24+N27+N30 -> 570 | O33: =SUM(C33:N33) -> 6840
B34: Actual | C34: =C25+C28+C31 -> 435 | D34: =D25+D28+D31 -> 508 | E34: =E25+E28+E31 -> 350 | F34: =F25+F28+F31 -> 0 | G34: =G25+G28+G31 -> 0 | H34: =H25+H28+H31 -> 0 | I34: =I25+I28+I31 -> 0 | J34: =J25+J28+J31 -> 0 | ... N34: =N25+N28+N31 -> 0 | O34: =SUM(C34:N34) -> 1293
B35: Difference | C35: =C34-C33 -> -135 | D35: =D34-D33 -> -62 | E35: =E34-E33 -> -220 | F35: =F34-F33 -> -570 | G35: =G34-G33 -> -570 | H35: =H34-H33 -> -570 | I35: =I34-I33 -> -570 | J35: =J34-J33 -> -570 | ... O35: =O34-O33 -> -5547
A37: FOOD
A38: =Setup!A29 -> Groceries | B38: Budget | C38: =Setup!C29 -> 650 | D38: =Setup!C29 -> 650 | E38: =Setup!C29 -> 650 | F38: =Setup!C29 -> 650 | G38: =Setup!C29 -> 650 | H38: =Setup!C29 -> 650 | I38: =Setup!C29 -> 650 | J38: =Setup!C29 -> 650 | K38: =Setup!C29 -> 650 | L38: =Setup!C29 -> 650 | M38: =Setup!C29 -> 650 | N38: =Setup!C29 -> 650 | O38: =SUM(C38:N38) -> 7800
B39: Actual | C39: =SUMIFS(Transactions!$D$5:$D$504,Transactions!$C$5:$C$504,$A38,Transactions!$F$5:$F$504,1,Transactions!$G$5:$G$504,YEAR(Setup!$B$18)) -> 315 | D39: =SUMIFS(Transactions!$D$5:$D$504,Transactions!$C$5:$C$504,$A38,Transactions!$F$5:$F$504,2,Transactions!$G$5:$G$504,YEAR(Setup!$B$18)) -> 342 | E39: =SUMIFS(Transactions!$D$5:$D$504,Transactions!$C$5:$C$504,$A38,Transactions!$F$5:$F$504,3,Transactions!$G$5:$G$504,YEAR(Setup!$B$18)) -> 298 | F39: =SUMIFS(Transactions!$D$5:$D$504,Transactions!$C$5:$C$504,$A38,Transactions!$F$5:$F$504,4,Transactions!$G$5:$G$504,YEAR(Setup!$B$18)) -> 0 | G39: =SUMIFS(Transactions!$D$5:$D$504,Transactions!$C$5:$C$504,$A38,Transactions!$F$5:$F$504,5,Transactions!$G$5:$G$504,YEAR(Setup!$B$18)) -> 0 | H39: =SUMIFS(Transactions!$D$5:$D$504,Transactions!$C$5:$C$504,$A38,Transactions!$F$5:$F$504,6,Transactions!$G$5:$G$504,YEAR(Setup!$B$18)) -> 0 | I39: =SUMIFS(Transactions!$D$5:$D$504,Transactions!$C$5:$C$504,$A38,Transactions!$F$5:$F$504,7,Transactions!$G$5:$G$504,YEAR(Setup!$B$18)) -> 0 | J39: =SUMIFS(Transactions!$D$5:$D$504,Transactions!$C$5:$C$504,$A38,Transactions!$F$5:$F$504,8,Transactions!$G$5:$G$504,YEAR(Setup!$B$18)) -> 0 | K39: =SUMIFS(Transactions!$D$5:$D$504,Transactions!$C$5:$C$504,$A38,Transactions!$F$5:$F$504,9,Transactions!$G$5:$G$504,YEAR(Setup!$B$18)) -> 0 | L39: =SUMIFS(Transactions!$D$5:$D$504,Transactions!$C$5:$C$504,$A38,Transactions!$F$5:$F$504,10,Transactions!$G$5:$G$504,YEAR(Setup!$B$18)) -> 0 | M39: =SUMIFS(Transactions!$D$5:$D$504,Transactions!$C$5:$C$504,$A38,Transactions!$F$5:$F$504,11,Transactions!$G$5:$G$504,YEAR(Setup!$B$18)) -> 0 | N39: =SUMIFS(Transactions!$D$5:$D$504,Transactions!$C$5:$C$504,$A38,Transactions!$F$5:$F$504,12,Transactions!$G$5:$G$504,YEAR(Setup!$B$18)) -> 0 | O39: =SUM(C39:N39) -> 955
B40: Difference | C40: =C39-C38 -> -335 | D40: =D39-D38 -> -308 | E40: =E39-E38 -> -352 | F40: =F39-F38 -> -650 | G40: =G39-G38 -> -650 | H40: =H39-H38 -> -650 | I40: =I39-I38 -> -650 | J40: =J39-J38 -> -650 | ... O40: =O39-O38 -> -6845
A41: =Setup!A30 -> Dining Out | B41: Budget | C41: =Setup!C30 -> 220 | D41: =Setup!C30 -> 220 | E41: =Setup!C30 -> 220 | F41: =Setup!C30 -> 220 | G41: =Setup!C30 -> 220 | H41: =Setup!C30 -> 220 | I41: =Setup!C30 -> 220 | J41: =Setup!C30 -> 220 | K41: =Setup!C30 -> 220 | L41: =Setup!C30 -> 220 | M41: =Setup!C30 -> 220 | N41: =Setup!C30 -> 220 | O41: =SUM(C41:N41) -> 2640
B42: Actual | C42: =SUMIFS(Transactions!$D$5:$D$504,Transactions!$C$5:$C$504,$A41,Transactions!$F$5:$F$504,1,Transactions!$G$5:$G$504,YEAR(Setup!$B$18)) -> 0 | D42: =SUMIFS(Transactions!$D$5:$D$504,Transactions!$C$5:$C$504,$A41,Transactions!$F$5:$F$504,2,Transactions!$G$5:$G$504,YEAR(Setup!$B$18)) -> 95 | E42: =SUMIFS(Transactions!$D$5:$D$504,Transactions!$C$5:$C$504,$A41,Transactions!$F$5:$F$504,3,Transactions!$G$5:$G$504,YEAR(Setup!$B$18)) -> 140 | F42: =SUMIFS(Transactions!$D$5:$D$504,Transactions!$C$5:$C$504,$A41,Transactions!$F$5:$F$504,4,Transactions!$G$5:$G$504,YEAR(Setup!$B$18)) -> 0 | G42: =SUMIFS(Transactions!$D$5:$D$504,Transactions!$C$5:$C$504,$A41,Transactions!$F$5:$F$504,5,Transactions!$G$5:$G$504,YEAR(Setup!$B$18)) -> 0 | H42: =SUMIFS(Transactions!$D$5:$D$504,Transactions!$C$5:$C$504,$A41,Transactions!$F$5:$F$504,6,Transactions!$G$5:$G$504,YEAR(Setup!$B$18)) -> 0 | I42: =SUMIFS(Transactions!$D$5:$D$504,Transactions!$C$5:$C$504,$A41,Transactions!$F$5:$F$504,7,Transactions!$G$5:$G$504,YEAR(Setup!$B$18)) -> 0 | J42: =SUMIFS(Transactions!$D$5:$D$504,Transactions!$C$5:$C$504,$A41,Transactions!$F$5:$F$504,8,Transactions!$G$5:$G$504,YEAR(Setup!$B$18)) -> 0 | K42: =SUMIFS(Transactions!$D$5:$D$504,Transactions!$C$5:$C$504,$A41,Transactions!$F$5:$F$504,9,Transactions!$G$5:$G$504,YEAR(Setup!$B$18)) -> 0 | L42: =SUMIFS(Transactions!$D$5:$D$504,Transactions!$C$5:$C$504,$A41,Transactions!$F$5:$F$504,10,Transactions!$G$5:$G$504,YEAR(Setup!$B$18)) -> 0 | M42: =SUMIFS(Transactions!$D$5:$D$504,Transactions!$C$5:$C$504,$A41,Transactions!$F$5:$F$504,11,Transactions!$G$5:$G$504,YEAR(Setup!$B$18)) -> 0 | N42: =SUMIFS(Transactions!$D$5:$D$504,Transactions!$C$5:$C$504,$A41,Transactions!$F$5:$F$504,12,Transactions!$G$5:$G$504,YEAR(Setup!$B$18)) -> 0 | O42: =SUM(C42:N42) -> 235
B43: Difference | C43: =C42-C41 -> -220 | D43: =D42-D41 -> -125 | E43: =E42-E41 -> -80 | F43: =F42-F41 -> -220 | G43: =G42-G41 -> -220 | H43: =H42-H41 -> -220 | I43: =I42-I41 -> -220 | J43: =J42-J41 -> -220 | ... O43: =O42-O41 -> -2405
A44: Food Total | B44: Budget | C44: =C38+C41 -> 870 | D44: =D38+D41 -> 870 | E44: =E38+E41 -> 870 | F44: =F38+F41 -> 870 | G44: =G38+G41 -> 870 | H44: =H38+H41 -> 870 | I44: =I38+I41 -> 870 | J44: =J38+J41 -> 870 | ... N44: =N38+N41 -> 870 | O44: =SUM(C44:N44) -> 10440
B45: Actual | C45: =C39+C42 -> 315 | D45: =D39+D42 -> 437 | E45: =E39+E42 -> 438 | F45: =F39+F42 -> 0 | G45: =G39+G42 -> 0 | H45: =H39+H42 -> 0 | I45: =I39+I42 -> 0 | J45: =J39+J42 -> 0 | ... N45: =N39+N42 -> 0 | O45: =SUM(C45:N45) -> 1190
B46: Difference | C46: =C45-C44 -> -555 | D46: =D45-D44 -> -433 | E46: =E45-E44 -> -432 | F46: =F45-F44 -> -870 | G46: =G45-G44 -> -870 | H46: =H45-H44 -> -870 | I46: =I45-I44 -> -870 | J46: =J45-J44 -> -870 | ... O46: =O45-O44 -> -9250
A48: INSURANCE
A49: =Setup!A31 -> Health Insurance | B49: Budget | C49: =Setup!C31 -> 340 | D49: =Setup!C31 -> 340 | E49: =Setup!C31 -> 340 | F49: =Setup!C31 -> 340 | G49: =Setup!C31 -> 340 | H49: =Setup!C31 -> 340 | I49: =Setup!C31 -> 340 | J49: =Setup!C31 -> 340 | K49: =Setup!C31 -> 340 | L49: =Setup!C31 -> 340 | M49: =Setup!C31 -> 340 | N49: =Setup!C31 -> 340 | O49: =SUM(C49:N49) -> 4080
B50: Actual | C50: =SUMIFS(Transactions!$D$5:$D$504,Transactions!$C$5:$C$504,$A49,Transactions!$F$5:$F$504,1,Transactions!$G$5:$G$504,YEAR(Setup!$B$18)) -> 340 | D50: =SUMIFS(Transactions!$D$5:$D$504,Transactions!$C$5:$C$504,$A49,Transactions!$F$5:$F$504,2,Transactions!$G$5:$G$504,YEAR(Setup!$B$18)) -> 340 | E50: =SUMIFS(Transactions!$D$5:$D$504,Transactions!$C$5:$C$504,$A49,Transactions!$F$5:$F$504,3,Transactions!$G$5:$G$504,YEAR(Setup!$B$18)) -> 340 | F50: =SUMIFS(Transactions!$D$5:$D$504,Transactions!$C$5:$C$504,$A49,Transactions!$F$5:$F$504,4,Transactions!$G$5:$G$504,YEAR(Setup!$B$18)) -> 0 | G50: =SUMIFS(Transactions!$D$5:$D$504,Transactions!$C$5:$C$504,$A49,Transactions!$F$5:$F$504,5,Transactions!$G$5:$G$504,YEAR(Setup!$B$18)) -> 0 | H50: =SUMIFS(Transactions!$D$5:$D$504,Transactions!$C$5:$C$504,$A49,Transactions!$F$5:$F$504,6,Transactions!$G$5:$G$504,YEAR(Setup!$B$18)) -> 0 | I50: =SUMIFS(Transactions!$D$5:$D$504,Transactions!$C$5:$C$504,$A49,Transactions!$F$5:$F$504,7,Transactions!$G$5:$G$504,YEAR(Setup!$B$18)) -> 0 | J50: =SUMIFS(Transactions!$D$5:$D$504,Transactions!$C$5:$C$504,$A49,Transactions!$F$5:$F$504,8,Transactions!$G$5:$G$504,YEAR(Setup!$B$18)) -> 0 | K50: =SUMIFS(Transactions!$D$5:$D$504,Transactions!$C$5:$C$504,$A49,Transactions!$F$5:$F$504,9,Transactions!$G$5:$G$504,YEAR(Setup!$B$18)) -> 0 | L50: =SUMIFS(Transactions!$D$5:$D$504,Transactions!$C$5:$C$504,$A49,Transactions!$F$5:$F$504,10,Transactions!$G$5:$G$504,YEAR(Setup!$B$18)) -> 0 | M50: =SUMIFS(Transactions!$D$5:$D$504,Transactions!$C$5:$C$504,$A49,Transactions!$F$5:$F$504,11,Transactions!$G$5:$G$504,YEAR(Setup!$B$18)) -> 0 | N50: =SUMIFS(Transactions!$D$5:$D$504,Transactions!$C$5:$C$504,$A49,Transactions!$F$5:$F$504,12,Transactions!$G$5:$G$504,YEAR(Setup!$B$18)) -> 0 | O50: =SUM(C50:N50) -> 1020
B51: Difference | C51: =C50-C49 -> 0 | D51: =D50-D49 -> 0 | E51: =E50-E49 -> 0 | F51: =F50-F49 -> -340 | G51: =G50-G49 -> -340 | H51: =H50-H49 -> -340 | I51: =I50-I49 -> -340 | J51: =J50-J49 -> -340 | ... O51: =O50-O49 -> -3060
A52: =Setup!A32 -> Auto Insurance | B52: Budget | C52: =Setup!C32 -> 120 | D52: =Setup!C32 -> 120 | E52: =Setup!C32 -> 120 | F52: =Setup!C32 -> 120 | G52: =Setup!C32 -> 120 | H52: =Setup!C32 -> 120 | I52: =Setup!C32 -> 120 | J52: =Setup!C32 -> 120 | K52: =Setup!C32 -> 120 | L52: =Setup!C32 -> 120 | M52: =Setup!C32 -> 120 | N52: =Setup!C32 -> 120 | O52: =SUM(C52:N52) -> 1440
B53: Actual | C53: =SUMIFS(Transactions!$D$5:$D$504,Transactions!$C$5:$C$504,$A52,Transactions!$F$5:$F$504,1,Transactions!$G$5:$G$504,YEAR(Setup!$B$18)) -> 0 | D53: =SUMIFS(Transactions!$D$5:$D$504,Transactions!$C$5:$C$504,$A52,Transactions!$F$5:$F$504,2,Transactions!$G$5:$G$504,YEAR(Setup!$B$18)) -> 120 | E53: =SUMIFS(Transactions!$D$5:$D$504,Transactions!$C$5:$C$504,$A52,Transactions!$F$5:$F$504,3,Transactions!$G$5:$G$504,YEAR(Setup!$B$18)) -> 120 | F53: =SUMIFS(Transactions!$D$5:$D$504,Transactions!$C$5:$C$504,$A52,Transactions!$F$5:$F$504,4,Transactions!$G$5:$G$504,YEAR(Setup!$B$18)) -> 0 | G53: =SUMIFS(Transactions!$D$5:$D$504,Transactions!$C$5:$C$504,$A52,Transactions!$F$5:$F$504,5,Transactions!$G$5:$G$504,YEAR(Setup!$B$18)) -> 0 | H53: =SUMIFS(Transactions!$D$5:$D$504,Transactions!$C$5:$C$504,$A52,Transactions!$F$5:$F$504,6,Transactions!$G$5:$G$504,YEAR(Setup!$B$18)) -> 0 | I53: =SUMIFS(Transactions!$D$5:$D$504,Transactions!$C$5:$C$504,$A52,Transactions!$F$5:$F$504,7,Transactions!$G$5:$G$504,YEAR(Setup!$B$18)) -> 0 | J53: =SUMIFS(Transactions!$D$5:$D$504,Transactions!$C$5:$C$504,$A52,Transactions!$F$5:$F$504,8,Transactions!$G$5:$G$504,YEAR(Setup!$B$18)) -> 0 | K53: =SUMIFS(Transactions!$D$5:$D$504,Transactions!$C$5:$C$504,$A52,Transactions!$F$5:$F$504,9,Transactions!$G$5:$G$504,YEAR(Setup!$B$18)) -> 0 | L53: =SUMIFS(Transactions!$D$5:$D$504,Transactions!$C$5:$C$504,$A52,Transactions!$F$5:$F$504,10,Transactions!$G$5:$G$504,YEAR(Setup!$B$18)) -> 0 | M53: =SUMIFS(Transactions!$D$5:$D$504,Transactions!$C$5:$C$504,$A52,Transactions!$F$5:$F$504,11,Transactions!$G$5:$G$504,YEAR(Setup!$B$18)) -> 0 | N53: =SUMIFS(Transactions!$D$5:$D$504,Transactions!$C$5:$C$504,$A52,Transactions!$F$5:$F$504,12,Transactions!$G$5:$G$504,YEAR(Setup!$B$18)) -> 0 | O53: =SUM(C53:N53) -> 240
B54: Difference | C54: =C53-C52 -> -120 | D54: =D53-D52 -> 0 | E54: =E53-E52 -> 0 | F54: =F53-F52 -> -120 | G54: =G53-G52 -> -120 | H54: =H53-H52 -> -120 | I54: =I53-I52 -> -120 | J54: =J53-J52 -> -120 | ... O54: =O53-O52 -> -1200
A55: =Setup!A33 -> Life Insurance | B55: Budget | C55: =Setup!C33 -> 45 | D55: =Setup!C33 -> 45 | E55: =Setup!C33 -> 45 | F55: =Setup!C33 -> 45 | G55: =Setup!C33 -> 45 | H55: =Setup!C33 -> 45 | I55: =Setup!C33 -> 45 | J55: =Setup!C33 -> 45 | K55: =Setup!C33 -> 45 | L55: =Setup!C33 -> 45 | M55: =Setup!C33 -> 45 | N55: =Setup!C33 -> 45 | O55: =SUM(C55:N55) -> 540
B56: Actual | C56: =SUMIFS(Transactions!$D$5:$D$504,Transactions!$C$5:$C$504,$A55,Transactions!$F$5:$F$504,1,Transactions!$G$5:$G$504,YEAR(Setup!$B$18)) -> 45 | D56: =SUMIFS(Transactions!$D$5:$D$504,Transactions!$C$5:$C$504,$A55,Transactions!$F$5:$F$504,2,Transactions!$G$5:$G$504,YEAR(Setup!$B$18)) -> 0 | E56: =SUMIFS(Transactions!$D$5:$D$504,Transactions!$C$5:$C$504,$A55,Transactions!$F$5:$F$504,3,Transactions!$G$5:$G$504,YEAR(Setup!$B$18)) -> 0 | F56: =SUMIFS(Transactions!$D$5:$D$504,Transactions!$C$5:$C$504,$A55,Transactions!$F$5:$F$504,4,Transactions!$G$5:$G$504,YEAR(Setup!$B$18)) -> 0 | G56: =SUMIFS(Transactions!$D$5:$D$504,Transactions!$C$5:$C$504,$A55,Transactions!$F$5:$F$504,5,Transactions!$G$5:$G$504,YEAR(Setup!$B$18)) -> 0 | H56: =SUMIFS(Transactions!$D$5:$D$504,Transactions!$C$5:$C$504,$A55,Transactions!$F$5:$F$504,6,Transactions!$G$5:$G$504,YEAR(Setup!$B$18)) -> 0 | I56: =SUMIFS(Transactions!$D$5:$D$504,Transactions!$C$5:$C$504,$A55,Transactions!$F$5:$F$504,7,Transactions!$G$5:$G$504,YEAR(Setup!$B$18)) -> 0 | J56: =SUMIFS(Transactions!$D$5:$D$504,Transactions!$C$5:$C$504,$A55,Transactions!$F$5:$F$504,8,Transactions!$G$5:$G$504,YEAR(Setup!$B$18)) -> 0 | K56: =SUMIFS(Transactions!$D$5:$D$504,Transactions!$C$5:$C$504,$A55,Transactions!$F$5:$F$504,9,Transactions!$G$5:$G$504,YEAR(Setup!$B$18)) -> 0 | L56: =SUMIFS(Transactions!$D$5:$D$504,Transactions!$C$5:$C$504,$A55,Transactions!$F$5:$F$504,10,Transactions!$G$5:$G$504,YEAR(Setup!$B$18)) -> 0 | M56: =SUMIFS(Transactions!$D$5:$D$504,Transactions!$C$5:$C$504,$A55,Transactions!$F$5:$F$504,11,Transactions!$G$5:$G$504,YEAR(Setup!$B$18)) -> 0 | N56: =SUMIFS(Transactions!$D$5:$D$504,Transactions!$C$5:$C$504,$A55,Transactions!$F$5:$F$504,12,Transactions!$G$5:$G$504,YEAR(Setup!$B$18)) -> 0 | O56: =SUM(C56:N56) -> 45
B57: Difference | C57: =C56-C55 -> 0 | D57: =D56-D55 -> -45 | E57: =E56-E55 -> -45 | F57: =F56-F55 -> -45 | G57: =G56-G55 -> -45 | H57: =H56-H55 -> -45 | I57: =I56-I55 -> -45 | J57: =J56-J55 -> -45 | ... O57: =O56-O55 -> -495
A58: Insurance Total | B58: Budget | C58: =C49+C52+C55 -> 505 | D58: =D49+D52+D55 -> 505 | E58: =E49+E52+E55 -> 505 | F58: =F49+F52+F55 -> 505 | G58: =G49+G52+G55 -> 505 | H58: =H49+H52+H55 -> 505 | I58: =I49+I52+I55 -> 505 | J58: =J49+J52+J55 -> 505 | ... N58: =N49+N52+N55 -> 505 | O58: =SUM(C58:N58) -> 6060
B59: Actual | C59: =C50+C53+C56 -> 385 | D59: =D50+D53+D56 -> 460 | E59: =E50+E53+E56 -> 460 | F59: =F50+F53+F56 -> 0 | G59: =G50+G53+G56 -> 0 | H59: =H50+H53+H56 -> 0 | I59: =I50+I53+I56 -> 0 | J59: =J50+J53+J56 -> 0 | ... N59: =N50+N53+N56 -> 0 | O59: =SUM(C59:N59) -> 1305
B60: Difference | C60: =C59-C58 -> -120 | D60: =D59-D58 -> -45 | E60: =E59-E58 -> -45 | F60: =F59-F58 -> -505 | G60: =G59-G58 -> -505 | H60: =H59-H58 -> -505 | I60: =I59-I58 -> -505 | J60: =J59-J58 -> -505 | ... O60: =O59-O58 -> -4755
A62: DEBT
A63: =Setup!A34 -> Credit Card Payment | B63: Budget | C63: =Setup!C34 -> 150 | D63: =Setup!C34 -> 150 | E63: =Setup!C34 -> 150 | F63: =Setup!C34 -> 150 | G63: =Setup!C34 -> 150 | H63: =Setup!C34 -> 150 | I63: =Setup!C34 -> 150 | J63: =Setup!C34 -> 150 | K63: =Setup!C34 -> 150 | L63: =Setup!C34 -> 150 | M63: =Setup!C34 -> 150 | N63: =Setup!C34 -> 150 | O63: =SUM(C63:N63) -> 1800
B64: Actual | C64: =SUMIFS(Transactions!$D$5:$D$504,Transactions!$C$5:$C$504,$A63,Transactions!$F$5:$F$504,1,Transactions!$G$5:$G$504,YEAR(Setup!$B$18)) -> 150 | D64: =SUMIFS(Transactions!$D$5:$D$504,Transactions!$C$5:$C$504,$A63,Transactions!$F$5:$F$504,2,Transactions!$G$5:$G$504,YEAR(Setup!$B$18)) -> 165 | E64: =SUMIFS(Transactions!$D$5:$D$504,Transactions!$C$5:$C$504,$A63,Transactions!$F$5:$F$504,3,Transactions!$G$5:$G$504,YEAR(Setup!$B$18)) -> 150 | F64: =SUMIFS(Transactions!$D$5:$D$504,Transactions!$C$5:$C$504,$A63,Transactions!$F$5:$F$504,4,Transactions!$G$5:$G$504,YEAR(Setup!$B$18)) -> 0 | G64: =SUMIFS(Transactions!$D$5:$D$504,Transactions!$C$5:$C$504,$A63,Transactions!$F$5:$F$504,5,Transactions!$G$5:$G$504,YEAR(Setup!$B$18)) -> 0 | H64: =SUMIFS(Transactions!$D$5:$D$504,Transactions!$C$5:$C$504,$A63,Transactions!$F$5:$F$504,6,Transactions!$G$5:$G$504,YEAR(Setup!$B$18)) -> 0 | I64: =SUMIFS(Transactions!$D$5:$D$504,Transactions!$C$5:$C$504,$A63,Transactions!$F$5:$F$504,7,Transactions!$G$5:$G$504,YEAR(Setup!$B$18)) -> 0 | J64: =SUMIFS(Transactions!$D$5:$D$504,Transactions!$C$5:$C$504,$A63,Transactions!$F$5:$F$504,8,Transactions!$G$5:$G$504,YEAR(Setup!$B$18)) -> 0 | K64: =SUMIFS(Transactions!$D$5:$D$504,Transactions!$C$5:$C$504,$A63,Transactions!$F$5:$F$504,9,Transactions!$G$5:$G$504,YEAR(Setup!$B$18)) -> 0 | L64: =SUMIFS(Transactions!$D$5:$D$504,Transactions!$C$5:$C$504,$A63,Transactions!$F$5:$F$504,10,Transactions!$G$5:$G$504,YEAR(Setup!$B$18)) -> 0 | M64: =SUMIFS(Transactions!$D$5:$D$504,Transactions!$C$5:$C$504,$A63,Transactions!$F$5:$F$504,11,Transactions!$G$5:$G$504,YEAR(Setup!$B$18)) -> 0 | N64: =SUMIFS(Transactions!$D$5:$D$504,Transactions!$C$5:$C$504,$A63,Transactions!$F$5:$F$504,12,Transactions!$G$5:$G$504,YEAR(Setup!$B$18)) -> 0 | O64: =SUM(C64:N64) -> 465
B65: Difference | C65: =C64-C63 -> 0 | D65: =D64-D63 -> 15 | E65: =E64-E63 -> 0 | F65: =F64-F63 -> -150 | G65: =G64-G63 -> -150 | H65: =H64-H63 -> -150 | I65: =I64-I63 -> -150 | J65: =J64-J63 -> -150 | ... O65: =O64-O63 -> -1335
A66: =Setup!A35 -> Student Loan Payment | B66: Budget | C66: =Setup!C35 -> 220 | D66: =Setup!C35 -> 220 | E66: =Setup!C35 -> 220 | F66: =Setup!C35 -> 220 | G66: =Setup!C35 -> 220 | H66: =Setup!C35 -> 220 | I66: =Setup!C35 -> 220 | J66: =Setup!C35 -> 220 | K66: =Setup!C35 -> 220 | L66: =Setup!C35 -> 220 | M66: =Setup!C35 -> 220 | N66: =Setup!C35 -> 220 | O66: =SUM(C66:N66) -> 2640
B67: Actual | C67: =SUMIFS(Transactions!$D$5:$D$504,Transactions!$C$5:$C$504,$A66,Transactions!$F$5:$F$504,1,Transactions!$G$5:$G$504,YEAR(Setup!$B$18)) -> 220 | D67: =SUMIFS(Transactions!$D$5:$D$504,Transactions!$C$5:$C$504,$A66,Transactions!$F$5:$F$504,2,Transactions!$G$5:$G$504,YEAR(Setup!$B$18)) -> 220 | E67: =SUMIFS(Transactions!$D$5:$D$504,Transactions!$C$5:$C$504,$A66,Transactions!$F$5:$F$504,3,Transactions!$G$5:$G$504,YEAR(Setup!$B$18)) -> 220 | F67: =SUMIFS(Transactions!$D$5:$D$504,Transactions!$C$5:$C$504,$A66,Transactions!$F$5:$F$504,4,Transactions!$G$5:$G$504,YEAR(Setup!$B$18)) -> 0 | G67: =SUMIFS(Transactions!$D$5:$D$504,Transactions!$C$5:$C$504,$A66,Transactions!$F$5:$F$504,5,Transactions!$G$5:$G$504,YEAR(Setup!$B$18)) -> 0 | H67: =SUMIFS(Transactions!$D$5:$D$504,Transactions!$C$5:$C$504,$A66,Transactions!$F$5:$F$504,6,Transactions!$G$5:$G$504,YEAR(Setup!$B$18)) -> 0 | I67: =SUMIFS(Transactions!$D$5:$D$504,Transactions!$C$5:$C$504,$A66,Transactions!$F$5:$F$504,7,Transactions!$G$5:$G$504,YEAR(Setup!$B$18)) -> 0 | J67: =SUMIFS(Transactions!$D$5:$D$504,Transactions!$C$5:$C$504,$A66,Transactions!$F$5:$F$504,8,Transactions!$G$5:$G$504,YEAR(Setup!$B$18)) -> 0 | K67: =SUMIFS(Transactions!$D$5:$D$504,Transactions!$C$5:$C$504,$A66,Transactions!$F$5:$F$504,9,Transactions!$G$5:$G$504,YEAR(Setup!$B$18)) -> 0 | L67: =SUMIFS(Transactions!$D$5:$D$504,Transactions!$C$5:$C$504,$A66,Transactions!$F$5:$F$504,10,Transactions!$G$5:$G$504,YEAR(Setup!$B$18)) -> 0 | M67: =SUMIFS(Transactions!$D$5:$D$504,Transactions!$C$5:$C$504,$A66,Transactions!$F$5:$F$504,11,Transactions!$G$5:$G$504,YEAR(Setup!$B$18)) -> 0 | N67: =SUMIFS(Transactions!$D$5:$D$504,Transactions!$C$5:$C$504,$A66,Transactions!$F$5:$F$504,12,Transactions!$G$5:$G$504,YEAR(Setup!$B$18)) -> 0 | O67: =SUM(C67:N67) -> 660
B68: Difference | C68: =C67-C66 -> 0 | D68: =D67-D66 -> 0 | E68: =E67-E66 -> 0 | F68: =F67-F66 -> -220 | G68: =G67-G66 -> -220 | H68: =H67-H66 -> -220 | I68: =I67-I66 -> -220 | J68: =J67-J66 -> -220 | ... O68: =O67-O66 -> -1980
A69: Debt Total | B69: Budget | C69: =C63+C66 -> 370 | D69: =D63+D66 -> 370 | E69: =E63+E66 -> 370 | F69: =F63+F66 -> 370 | G69: =G63+G66 -> 370 | H69: =H63+H66 -> 370 | I69: =I63+I66 -> 370 | J69: =J63+J66 -> 370 | ... N69: =N63+N66 -> 370 | O69: =SUM(C69:N69) -> 4440
B70: Actual | C70: =C64+C67 -> 370 | D70: =D64+D67 -> 385 | E70: =E64+E67 -> 370 | F70: =F64+F67 -> 0 | G70: =G64+G67 -> 0 | H70: =H64+H67 -> 0 | I70: =I64+I67 -> 0 | J70: =J64+J67 -> 0 | ... N70: =N64+N67 -> 0 | O70: =SUM(C70:N70) -> 1125
B71: Difference | C71: =C70-C69 -> 0 | D71: =D70-D69 -> 15 | E71: =E70-E69 -> 0 | F71: =F70-F69 -> -370 | G71: =G70-G69 -> -370 | H71: =H70-H69 -> -370 | I71: =I70-I69 -> -370 | J71: =J70-J69 -> -370 | ... O71: =O70-O69 -> -3315
A73: SAVINGS AND INVESTING
A74: =Setup!A36 -> Emergency Fund | B74: Budget | C74: =Setup!C36 -> 200 | D74: =Setup!C36 -> 200 | E74: =Setup!C36 -> 200 | F74: =Setup!C36 -> 200 | G74: =Setup!C36 -> 200 | H74: =Setup!C36 -> 200 | I74: =Setup!C36 -> 200 | J74: =Setup!C36 -> 200 | K74: =Setup!C36 -> 200 | L74: =Setup!C36 -> 200 | M74: =Setup!C36 -> 200 | N74: =Setup!C36 -> 200 | O74: =SUM(C74:N74) -> 2400
B75: Actual | C75: =SUMIFS(Transactions!$D$5:$D$504,Transactions!$C$5:$C$504,$A74,Transactions!$F$5:$F$504,1,Transactions!$G$5:$G$504,YEAR(Setup!$B$18)) -> 200 | D75: =SUMIFS(Transactions!$D$5:$D$504,Transactions!$C$5:$C$504,$A74,Transactions!$F$5:$F$504,2,Transactions!$G$5:$G$504,YEAR(Setup!$B$18)) -> 0 | E75: =SUMIFS(Transactions!$D$5:$D$504,Transactions!$C$5:$C$504,$A74,Transactions!$F$5:$F$504,3,Transactions!$G$5:$G$504,YEAR(Setup!$B$18)) -> 0 | F75: =SUMIFS(Transactions!$D$5:$D$504,Transactions!$C$5:$C$504,$A74,Transactions!$F$5:$F$504,4,Transactions!$G$5:$G$504,YEAR(Setup!$B$18)) -> 0 | G75: =SUMIFS(Transactions!$D$5:$D$504,Transactions!$C$5:$C$504,$A74,Transactions!$F$5:$F$504,5,Transactions!$G$5:$G$504,YEAR(Setup!$B$18)) -> 0 | H75: =SUMIFS(Transactions!$D$5:$D$504,Transactions!$C$5:$C$504,$A74,Transactions!$F$5:$F$504,6,Transactions!$G$5:$G$504,YEAR(Setup!$B$18)) -> 0 | I75: =SUMIFS(Transactions!$D$5:$D$504,Transactions!$C$5:$C$504,$A74,Transactions!$F$5:$F$504,7,Transactions!$G$5:$G$504,YEAR(Setup!$B$18)) -> 0 | J75: =SUMIFS(Transactions!$D$5:$D$504,Transactions!$C$5:$C$504,$A74,Transactions!$F$5:$F$504,8,Transactions!$G$5:$G$504,YEAR(Setup!$B$18)) -> 0 | K75: =SUMIFS(Transactions!$D$5:$D$504,Transactions!$C$5:$C$504,$A74,Transactions!$F$5:$F$504,9,Transactions!$G$5:$G$504,YEAR(Setup!$B$18)) -> 0 | L75: =SUMIFS(Transactions!$D$5:$D$504,Transactions!$C$5:$C$504,$A74,Transactions!$F$5:$F$504,10,Transactions!$G$5:$G$504,YEAR(Setup!$B$18)) -> 0 | M75: =SUMIFS(Transactions!$D$5:$D$504,Transactions!$C$5:$C$504,$A74,Transactions!$F$5:$F$504,11,Transactions!$G$5:$G$504,YEAR(Setup!$B$18)) -> 0 | N75: =SUMIFS(Transactions!$D$5:$D$504,Transactions!$C$5:$C$504,$A74,Transactions!$F$5:$F$504,12,Transactions!$G$5:$G$504,YEAR(Setup!$B$18)) -> 0 | O75: =SUM(C75:N75) -> 200
B76: Difference | C76: =C75-C74 -> 0 | D76: =D75-D74 -> -200 | E76: =E75-E74 -> -200 | F76: =F75-F74 -> -200 | G76: =G75-G74 -> -200 | H76: =H75-H74 -> -200 | I76: =I75-I74 -> -200 | J76: =J75-J74 -> -200 | ... O76: =O75-O74 -> -2200
A77: =Setup!A37 -> Retirement 401k or IRA | B77: Budget | C77: =Setup!C37 -> 500 | D77: =Setup!C37 -> 500 | E77: =Setup!C37 -> 500 | F77: =Setup!C37 -> 500 | G77: =Setup!C37 -> 500 | H77: =Setup!C37 -> 500 | I77: =Setup!C37 -> 500 | J77: =Setup!C37 -> 500 | K77: =Setup!C37 -> 500 | L77: =Setup!C37 -> 500 | M77: =Setup!C37 -> 500 | N77: =Setup!C37 -> 500 | O77: =SUM(C77:N77) -> 6000
B78: Actual | C78: =SUMIFS(Transactions!$D$5:$D$504,Transactions!$C$5:$C$504,$A77,Transactions!$F$5:$F$504,1,Transactions!$G$5:$G$504,YEAR(Setup!$B$18)) -> 500 | D78: =SUMIFS(Transactions!$D$5:$D$504,Transactions!$C$5:$C$504,$A77,Transactions!$F$5:$F$504,2,Transactions!$G$5:$G$504,YEAR(Setup!$B$18)) -> 0 | E78: =SUMIFS(Transactions!$D$5:$D$504,Transactions!$C$5:$C$504,$A77,Transactions!$F$5:$F$504,3,Transactions!$G$5:$G$504,YEAR(Setup!$B$18)) -> 500 | F78: =SUMIFS(Transactions!$D$5:$D$504,Transactions!$C$5:$C$504,$A77,Transactions!$F$5:$F$504,4,Transactions!$G$5:$G$504,YEAR(Setup!$B$18)) -> 0 | G78: =SUMIFS(Transactions!$D$5:$D$504,Transactions!$C$5:$C$504,$A77,Transactions!$F$5:$F$504,5,Transactions!$G$5:$G$504,YEAR(Setup!$B$18)) -> 0 | H78: =SUMIFS(Transactions!$D$5:$D$504,Transactions!$C$5:$C$504,$A77,Transactions!$F$5:$F$504,6,Transactions!$G$5:$G$504,YEAR(Setup!$B$18)) -> 0 | I78: =SUMIFS(Transactions!$D$5:$D$504,Transactions!$C$5:$C$504,$A77,Transactions!$F$5:$F$504,7,Transactions!$G$5:$G$504,YEAR(Setup!$B$18)) -> 0 | J78: =SUMIFS(Transactions!$D$5:$D$504,Transactions!$C$5:$C$504,$A77,Transactions!$F$5:$F$504,8,Transactions!$G$5:$G$504,YEAR(Setup!$B$18)) -> 0 | K78: =SUMIFS(Transactions!$D$5:$D$504,Transactions!$C$5:$C$504,$A77,Transactions!$F$5:$F$504,9,Transactions!$G$5:$G$504,YEAR(Setup!$B$18)) -> 0 | L78: =SUMIFS(Transactions!$D$5:$D$504,Transactions!$C$5:$C$504,$A77,Transactions!$F$5:$F$504,10,Transactions!$G$5:$G$504,YEAR(Setup!$B$18)) -> 0 | M78: =SUMIFS(Transactions!$D$5:$D$504,Transactions!$C$5:$C$504,$A77,Transactions!$F$5:$F$504,11,Transactions!$G$5:$G$504,YEAR(Setup!$B$18)) -> 0 | N78: =SUMIFS(Transactions!$D$5:$D$504,Transactions!$C$5:$C$504,$A77,Transactions!$F$5:$F$504,12,Transactions!$G$5:$G$504,YEAR(Setup!$B$18)) -> 0 | O78: =SUM(C78:N78) -> 1000
B79: Difference | C79: =C78-C77 -> 0 | D79: =D78-D77 -> -500 | E79: =E78-E77 -> 0 | F79: =F78-F77 -> -500 | G79: =G78-G77 -> -500 | H79: =H78-H77 -> -500 | I79: =I78-I77 -> -500 | J79: =J78-J77 -> -500 | ... O79: =O78-O77 -> -5000
A80: =Setup!A38 -> Brokerage Investing | B80: Budget | C80: =Setup!C38 -> 300 | D80: =Setup!C38 -> 300 | E80: =Setup!C38 -> 300 | F80: =Setup!C38 -> 300 | G80: =Setup!C38 -> 300 | H80: =Setup!C38 -> 300 | I80: =Setup!C38 -> 300 | J80: =Setup!C38 -> 300 | K80: =Setup!C38 -> 300 | L80: =Setup!C38 -> 300 | M80: =Setup!C38 -> 300 | N80: =Setup!C38 -> 300 | O80: =SUM(C80:N80) -> 3600
B81: Actual | C81: =SUMIFS(Transactions!$D$5:$D$504,Transactions!$C$5:$C$504,$A80,Transactions!$F$5:$F$504,1,Transactions!$G$5:$G$504,YEAR(Setup!$B$18)) -> 0 | D81: =SUMIFS(Transactions!$D$5:$D$504,Transactions!$C$5:$C$504,$A80,Transactions!$F$5:$F$504,2,Transactions!$G$5:$G$504,YEAR(Setup!$B$18)) -> 0 | E81: =SUMIFS(Transactions!$D$5:$D$504,Transactions!$C$5:$C$504,$A80,Transactions!$F$5:$F$504,3,Transactions!$G$5:$G$504,YEAR(Setup!$B$18)) -> 300 | F81: =SUMIFS(Transactions!$D$5:$D$504,Transactions!$C$5:$C$504,$A80,Transactions!$F$5:$F$504,4,Transactions!$G$5:$G$504,YEAR(Setup!$B$18)) -> 0 | G81: =SUMIFS(Transactions!$D$5:$D$504,Transactions!$C$5:$C$504,$A80,Transactions!$F$5:$F$504,5,Transactions!$G$5:$G$504,YEAR(Setup!$B$18)) -> 0 | H81: =SUMIFS(Transactions!$D$5:$D$504,Transactions!$C$5:$C$504,$A80,Transactions!$F$5:$F$504,6,Transactions!$G$5:$G$504,YEAR(Setup!$B$18)) -> 0 | I81: =SUMIFS(Transactions!$D$5:$D$504,Transactions!$C$5:$C$504,$A80,Transactions!$F$5:$F$504,7,Transactions!$G$5:$G$504,YEAR(Setup!$B$18)) -> 0 | J81: =SUMIFS(Transactions!$D$5:$D$504,Transactions!$C$5:$C$504,$A80,Transactions!$F$5:$F$504,8,Transactions!$G$5:$G$504,YEAR(Setup!$B$18)) -> 0 | K81: =SUMIFS(Transactions!$D$5:$D$504,Transactions!$C$5:$C$504,$A80,Transactions!$F$5:$F$504,9,Transactions!$G$5:$G$504,YEAR(Setup!$B$18)) -> 0 | L81: =SUMIFS(Transactions!$D$5:$D$504,Transactions!$C$5:$C$504,$A80,Transactions!$F$5:$F$504,10,Transactions!$G$5:$G$504,YEAR(Setup!$B$18)) -> 0 | M81: =SUMIFS(Transactions!$D$5:$D$504,Transactions!$C$5:$C$504,$A80,Transactions!$F$5:$F$504,11,Transactions!$G$5:$G$504,YEAR(Setup!$B$18)) -> 0 | N81: =SUMIFS(Transactions!$D$5:$D$504,Transactions!$C$5:$C$504,$A80,Transactions!$F$5:$F$504,12,Transactions!$G$5:$G$504,YEAR(Setup!$B$18)) -> 0 | O81: =SUM(C81:N81) -> 300
B82: Difference | C82: =C81-C80 -> -300 | D82: =D81-D80 -> -300 | E82: =E81-E80 -> 0 | F82: =F81-F80 -> -300 | G82: =G81-G80 -> -300 | H82: =H81-H80 -> -300 | I82: =I81-I80 -> -300 | J82: =J81-J80 -> -300 | ... O82: =O81-O80 -> -3300
A83: Savings and Investing Total | B83: Budget | C83: =C74+C77+C80 -> 1000 | D83: =D74+D77+D80 -> 1000 | E83: =E74+E77+E80 -> 1000 | F83: =F74+F77+F80 -> 1000 | G83: =G74+G77+G80 -> 1000 | H83: =H74+H77+H80 -> 1000 | I83: =I74+I77+I80 -> 1000 | J83: =J74+J77+J80 -> 1000 | ... N83: =N74+N77+N80 -> 1000 | O83: =SUM(C83:N83) -> 12000
B84: Actual | C84: =C75+C78+C81 -> 700 | D84: =D75+D78+D81 -> 0 | E84: =E75+E78+E81 -> 800 | F84: =F75+F78+F81 -> 0 | G84: =G75+G78+G81 -> 0 | H84: =H75+H78+H81 -> 0 | I84: =I75+I78+I81 -> 0 | J84: =J75+J78+J81 -> 0 | ... N84: =N75+N78+N81 -> 0 | O84: =SUM(C84:N84) -> 1500
B85: Difference | C85: =C84-C83 -> -300 | D85: =D84-D83 -> -1000 | E85: =E84-E83 -> -200 | F85: =F84-F83 -> -1000 | G85: =G84-G83 -> -1000 | H85: =H84-H83 -> -1000 | I85: =I84-I83 -> -1000 | J85: =J84-J83 -> -1000 | ... O85: =O84-O83 -> -10500
A87: PERSONAL
A88: =Setup!A39 -> Entertainment | B88: Budget | C88: =Setup!C39 -> 120 | D88: =Setup!C39 -> 120 | E88: =Setup!C39 -> 120 | F88: =Setup!C39 -> 120 | G88: =Setup!C39 -> 120 | H88: =Setup!C39 -> 120 | I88: =Setup!C39 -> 120 | J88: =Setup!C39 -> 120 | K88: =Setup!C39 -> 120 | L88: =Setup!C39 -> 120 | M88: =Setup!C39 -> 120 | N88: =Setup!C39 -> 120 | O88: =SUM(C88:N88) -> 1440
B89: Actual | C89: =SUMIFS(Transactions!$D$5:$D$504,Transactions!$C$5:$C$504,$A88,Transactions!$F$5:$F$504,1,Transactions!$G$5:$G$504,YEAR(Setup!$B$18)) -> 0 | D89: =SUMIFS(Transactions!$D$5:$D$504,Transactions!$C$5:$C$504,$A88,Transactions!$F$5:$F$504,2,Transactions!$G$5:$G$504,YEAR(Setup!$B$18)) -> 65 | E89: =SUMIFS(Transactions!$D$5:$D$504,Transactions!$C$5:$C$504,$A88,Transactions!$F$5:$F$504,3,Transactions!$G$5:$G$504,YEAR(Setup!$B$18)) -> 0 | F89: =SUMIFS(Transactions!$D$5:$D$504,Transactions!$C$5:$C$504,$A88,Transactions!$F$5:$F$504,4,Transactions!$G$5:$G$504,YEAR(Setup!$B$18)) -> 0 | G89: =SUMIFS(Transactions!$D$5:$D$504,Transactions!$C$5:$C$504,$A88,Transactions!$F$5:$F$504,5,Transactions!$G$5:$G$504,YEAR(Setup!$B$18)) -> 0 | H89: =SUMIFS(Transactions!$D$5:$D$504,Transactions!$C$5:$C$504,$A88,Transactions!$F$5:$F$504,6,Transactions!$G$5:$G$504,YEAR(Setup!$B$18)) -> 0 | I89: =SUMIFS(Transactions!$D$5:$D$504,Transactions!$C$5:$C$504,$A88,Transactions!$F$5:$F$504,7,Transactions!$G$5:$G$504,YEAR(Setup!$B$18)) -> 0 | J89: =SUMIFS(Transactions!$D$5:$D$504,Transactions!$C$5:$C$504,$A88,Transactions!$F$5:$F$504,8,Transactions!$G$5:$G$504,YEAR(Setup!$B$18)) -> 0 | K89: =SUMIFS(Transactions!$D$5:$D$504,Transactions!$C$5:$C$504,$A88,Transactions!$F$5:$F$504,9,Transactions!$G$5:$G$504,YEAR(Setup!$B$18)) -> 0 | L89: =SUMIFS(Transactions!$D$5:$D$504,Transactions!$C$5:$C$504,$A88,Transactions!$F$5:$F$504,10,Transactions!$G$5:$G$504,YEAR(Setup!$B$18)) -> 0 | M89: =SUMIFS(Transactions!$D$5:$D$504,Transactions!$C$5:$C$504,$A88,Transactions!$F$5:$F$504,11,Transactions!$G$5:$G$504,YEAR(Setup!$B$18)) -> 0 | N89: =SUMIFS(Transactions!$D$5:$D$504,Transactions!$C$5:$C$504,$A88,Transactions!$F$5:$F$504,12,Transactions!$G$5:$G$504,YEAR(Setup!$B$18)) -> 0 | O89: =SUM(C89:N89) -> 65
B90: Difference | C90: =C89-C88 -> -120 | D90: =D89-D88 -> -55 | E90: =E89-E88 -> -120 | F90: =F89-F88 -> -120 | G90: =G89-G88 -> -120 | H90: =H89-H88 -> -120 | I90: =I89-I88 -> -120 | J90: =J89-J88 -> -120 | ... O90: =O89-O88 -> -1375
A91: =Setup!A40 -> Subscriptions | B91: Budget | C91: =Setup!C40 -> 60 | D91: =Setup!C40 -> 60 | E91: =Setup!C40 -> 60 | F91: =Setup!C40 -> 60 | G91: =Setup!C40 -> 60 | H91: =Setup!C40 -> 60 | I91: =Setup!C40 -> 60 | J91: =Setup!C40 -> 60 | K91: =Setup!C40 -> 60 | L91: =Setup!C40 -> 60 | M91: =Setup!C40 -> 60 | N91: =Setup!C40 -> 60 | O91: =SUM(C91:N91) -> 720
B92: Actual | C92: =SUMIFS(Transactions!$D$5:$D$504,Transactions!$C$5:$C$504,$A91,Transactions!$F$5:$F$504,1,Transactions!$G$5:$G$504,YEAR(Setup!$B$18)) -> 58 | D92: =SUMIFS(Transactions!$D$5:$D$504,Transactions!$C$5:$C$504,$A91,Transactions!$F$5:$F$504,2,Transactions!$G$5:$G$504,YEAR(Setup!$B$18)) -> 0 | E92: =SUMIFS(Transactions!$D$5:$D$504,Transactions!$C$5:$C$504,$A91,Transactions!$F$5:$F$504,3,Transactions!$G$5:$G$504,YEAR(Setup!$B$18)) -> 0 | F92: =SUMIFS(Transactions!$D$5:$D$504,Transactions!$C$5:$C$504,$A91,Transactions!$F$5:$F$504,4,Transactions!$G$5:$G$504,YEAR(Setup!$B$18)) -> 0 | G92: =SUMIFS(Transactions!$D$5:$D$504,Transactions!$C$5:$C$504,$A91,Transactions!$F$5:$F$504,5,Transactions!$G$5:$G$504,YEAR(Setup!$B$18)) -> 0 | H92: =SUMIFS(Transactions!$D$5:$D$504,Transactions!$C$5:$C$504,$A91,Transactions!$F$5:$F$504,6,Transactions!$G$5:$G$504,YEAR(Setup!$B$18)) -> 0 | I92: =SUMIFS(Transactions!$D$5:$D$504,Transactions!$C$5:$C$504,$A91,Transactions!$F$5:$F$504,7,Transactions!$G$5:$G$504,YEAR(Setup!$B$18)) -> 0 | J92: =SUMIFS(Transactions!$D$5:$D$504,Transactions!$C$5:$C$504,$A91,Transactions!$F$5:$F$504,8,Transactions!$G$5:$G$504,YEAR(Setup!$B$18)) -> 0 | K92: =SUMIFS(Transactions!$D$5:$D$504,Transactions!$C$5:$C$504,$A91,Transactions!$F$5:$F$504,9,Transactions!$G$5:$G$504,YEAR(Setup!$B$18)) -> 0 | L92: =SUMIFS(Transactions!$D$5:$D$504,Transactions!$C$5:$C$504,$A91,Transactions!$F$5:$F$504,10,Transactions!$G$5:$G$504,YEAR(Setup!$B$18)) -> 0 | M92: =SUMIFS(Transactions!$D$5:$D$504,Transactions!$C$5:$C$504,$A91,Transactions!$F$5:$F$504,11,Transactions!$G$5:$G$504,YEAR(Setup!$B$18)) -> 0 | N92: =SUMIFS(Transactions!$D$5:$D$504,Transactions!$C$5:$C$504,$A91,Transactions!$F$5:$F$504,12,Transactions!$G$5:$G$504,YEAR(Setup!$B$18)) -> 0 | O92: =SUM(C92:N92) -> 58
B93: Difference | C93: =C92-C91 -> -2 | D93: =D92-D91 -> -60 | E93: =E92-E91 -> -60 | F93: =F92-F91 -> -60 | G93: =G92-G91 -> -60 | H93: =H92-H91 -> -60 | I93: =I92-I91 -> -60 | J93: =J92-J91 -> -60 | ... O93: =O92-O91 -> -662
A94: =Setup!A41 -> Personal Care | B94: Budget | C94: =Setup!C41 -> 80 | D94: =Setup!C41 -> 80 | E94: =Setup!C41 -> 80 | F94: =Setup!C41 -> 80 | G94: =Setup!C41 -> 80 | H94: =Setup!C41 -> 80 | I94: =Setup!C41 -> 80 | J94: =Setup!C41 -> 80 | K94: =Setup!C41 -> 80 | L94: =Setup!C41 -> 80 | M94: =Setup!C41 -> 80 | N94: =Setup!C41 -> 80 | O94: =SUM(C94:N94) -> 960
B95: Actual | C95: =SUMIFS(Transactions!$D$5:$D$504,Transactions!$C$5:$C$504,$A94,Transactions!$F$5:$F$504,1,Transactions!$G$5:$G$504,YEAR(Setup!$B$18)) -> 75 | D95: =SUMIFS(Transactions!$D$5:$D$504,Transactions!$C$5:$C$504,$A94,Transactions!$F$5:$F$504,2,Transactions!$G$5:$G$504,YEAR(Setup!$B$18)) -> 0 | E95: =SUMIFS(Transactions!$D$5:$D$504,Transactions!$C$5:$C$504,$A94,Transactions!$F$5:$F$504,3,Transactions!$G$5:$G$504,YEAR(Setup!$B$18)) -> 0 | F95: =SUMIFS(Transactions!$D$5:$D$504,Transactions!$C$5:$C$504,$A94,Transactions!$F$5:$F$504,4,Transactions!$G$5:$G$504,YEAR(Setup!$B$18)) -> 0 | G95: =SUMIFS(Transactions!$D$5:$D$504,Transactions!$C$5:$C$504,$A94,Transactions!$F$5:$F$504,5,Transactions!$G$5:$G$504,YEAR(Setup!$B$18)) -> 0 | H95: =SUMIFS(Transactions!$D$5:$D$504,Transactions!$C$5:$C$504,$A94,Transactions!$F$5:$F$504,6,Transactions!$G$5:$G$504,YEAR(Setup!$B$18)) -> 0 | I95: =SUMIFS(Transactions!$D$5:$D$504,Transactions!$C$5:$C$504,$A94,Transactions!$F$5:$F$504,7,Transactions!$G$5:$G$504,YEAR(Setup!$B$18)) -> 0 | J95: =SUMIFS(Transactions!$D$5:$D$504,Transactions!$C$5:$C$504,$A94,Transactions!$F$5:$F$504,8,Transactions!$G$5:$G$504,YEAR(Setup!$B$18)) -> 0 | K95: =SUMIFS(Transactions!$D$5:$D$504,Transactions!$C$5:$C$504,$A94,Transactions!$F$5:$F$504,9,Transactions!$G$5:$G$504,YEAR(Setup!$B$18)) -> 0 | L95: =SUMIFS(Transactions!$D$5:$D$504,Transactions!$C$5:$C$504,$A94,Transactions!$F$5:$F$504,10,Transactions!$G$5:$G$504,YEAR(Setup!$B$18)) -> 0 | M95: =SUMIFS(Transactions!$D$5:$D$504,Transactions!$C$5:$C$504,$A94,Transactions!$F$5:$F$504,11,Transactions!$G$5:$G$504,YEAR(Setup!$B$18)) -> 0 | N95: =SUMIFS(Transactions!$D$5:$D$504,Transactions!$C$5:$C$504,$A94,Transactions!$F$5:$F$504,12,Transactions!$G$5:$G$504,YEAR(Setup!$B$18)) -> 0 | O95: =SUM(C95:N95) -> 75
B96: Difference | C96: =C95-C94 -> -5 | D96: =D95-D94 -> -80 | E96: =E95-E94 -> -80 | F96: =F95-F94 -> -80 | G96: =G95-G94 -> -80 | H96: =H95-H94 -> -80 | I96: =I95-I94 -> -80 | J96: =J95-J94 -> -80 | ... O96: =O95-O94 -> -885
A97: =Setup!A42 -> Clothing | B97: Budget | C97: =Setup!C42 -> 100 | D97: =Setup!C42 -> 100 | E97: =Setup!C42 -> 100 | F97: =Setup!C42 -> 100 | G97: =Setup!C42 -> 100 | H97: =Setup!C42 -> 100 | I97: =Setup!C42 -> 100 | J97: =Setup!C42 -> 100 | K97: =Setup!C42 -> 100 | L97: =Setup!C42 -> 100 | M97: =Setup!C42 -> 100 | N97: =Setup!C42 -> 100 | O97: =SUM(C97:N97) -> 1200
B98: Actual | C98: =SUMIFS(Transactions!$D$5:$D$504,Transactions!$C$5:$C$504,$A97,Transactions!$F$5:$F$504,1,Transactions!$G$5:$G$504,YEAR(Setup!$B$18)) -> 0 | D98: =SUMIFS(Transactions!$D$5:$D$504,Transactions!$C$5:$C$504,$A97,Transactions!$F$5:$F$504,2,Transactions!$G$5:$G$504,YEAR(Setup!$B$18)) -> 0 | E98: =SUMIFS(Transactions!$D$5:$D$504,Transactions!$C$5:$C$504,$A97,Transactions!$F$5:$F$504,3,Transactions!$G$5:$G$504,YEAR(Setup!$B$18)) -> 110 | F98: =SUMIFS(Transactions!$D$5:$D$504,Transactions!$C$5:$C$504,$A97,Transactions!$F$5:$F$504,4,Transactions!$G$5:$G$504,YEAR(Setup!$B$18)) -> 0 | G98: =SUMIFS(Transactions!$D$5:$D$504,Transactions!$C$5:$C$504,$A97,Transactions!$F$5:$F$504,5,Transactions!$G$5:$G$504,YEAR(Setup!$B$18)) -> 0 | H98: =SUMIFS(Transactions!$D$5:$D$504,Transactions!$C$5:$C$504,$A97,Transactions!$F$5:$F$504,6,Transactions!$G$5:$G$504,YEAR(Setup!$B$18)) -> 0 | I98: =SUMIFS(Transactions!$D$5:$D$504,Transactions!$C$5:$C$504,$A97,Transactions!$F$5:$F$504,7,Transactions!$G$5:$G$504,YEAR(Setup!$B$18)) -> 0 | J98: =SUMIFS(Transactions!$D$5:$D$504,Transactions!$C$5:$C$504,$A97,Transactions!$F$5:$F$504,8,Transactions!$G$5:$G$504,YEAR(Setup!$B$18)) -> 0 | K98: =SUMIFS(Transactions!$D$5:$D$504,Transactions!$C$5:$C$504,$A97,Transactions!$F$5:$F$504,9,Transactions!$G$5:$G$504,YEAR(Setup!$B$18)) -> 0 | L98: =SUMIFS(Transactions!$D$5:$D$504,Transactions!$C$5:$C$504,$A97,Transactions!$F$5:$F$504,10,Transactions!$G$5:$G$504,YEAR(Setup!$B$18)) -> 0 | M98: =SUMIFS(Transactions!$D$5:$D$504,Transactions!$C$5:$C$504,$A97,Transactions!$F$5:$F$504,11,Transactions!$G$5:$G$504,YEAR(Setup!$B$18)) -> 0 | N98: =SUMIFS(Transactions!$D$5:$D$504,Transactions!$C$5:$C$504,$A97,Transactions!$F$5:$F$504,12,Transactions!$G$5:$G$504,YEAR(Setup!$B$18)) -> 0 | O98: =SUM(C98:N98) -> 110
B99: Difference | C99: =C98-C97 -> -100 | D99: =D98-D97 -> -100 | E99: =E98-E97 -> 10 | F99: =F98-F97 -> -100 | G99: =G98-G97 -> -100 | H99: =H98-H97 -> -100 | I99: =I98-I97 -> -100 | J99: =J98-J97 -> -100 | ... O99: =O98-O97 -> -1090
A100: Personal Total | B100: Budget | C100: =C88+C91+C94+C97 -> 360 | D100: =D88+D91+D94+D97 -> 360 | E100: =E88+E91+E94+E97 -> 360 | F100: =F88+F91+F94+F97 -> 360 | G100: =G88+G91+G94+G97 -> 360 | H100: =H88+H91+H94+H97 -> 360 | I100: =I88+I91+I94+I97 -> 360 | J100: =J88+J91+J94+J97 -> 360 | ... N100: =N88+N91+N94+N97 -> 360 | O100: =SUM(C100:N100) -> 4320
B101: Actual | C101: =C89+C92+C95+C98 -> 133 | D101: =D89+D92+D95+D98 -> 65 | E101: =E89+E92+E95+E98 -> 110 | F101: =F89+F92+F95+F98 -> 0 | G101: =G89+G92+G95+G98 -> 0 | H101: =H89+H92+H95+H98 -> 0 | I101: =I89+I92+I95+I98 -> 0 | J101: =J89+J92+J95+J98 -> 0 | ... N101: =N89+N92+N95+N98 -> 0 | O101: =SUM(C101:N101) -> 308
B102: Difference | C102: =C101-C100 -> -227 | D102: =D101-D100 -> -295 | E102: =E101-E100 -> -250 | F102: =F101-F100 -> -360 | G102: =G101-G100 -> -360 | H102: =H101-H100 -> -360 | I102: =I101-I100 -> -360 | J102: =J101-J100 -> -360 | ... O102: =O101-O100 -> -4012
A104: OTHER
A105: =Setup!A43 -> Gifts and Donations | B105: Budget | C105: =Setup!C43 -> 100 | D105: =Setup!C43 -> 100 | E105: =Setup!C43 -> 100 | F105: =Setup!C43 -> 100 | G105: =Setup!C43 -> 100 | H105: =Setup!C43 -> 100 | I105: =Setup!C43 -> 100 | J105: =Setup!C43 -> 100 | K105: =Setup!C43 -> 100 | L105: =Setup!C43 -> 100 | M105: =Setup!C43 -> 100 | N105: =Setup!C43 -> 100 | O105: =SUM(C105:N105) -> 1200
B106: Actual | C106: =SUMIFS(Transactions!$D$5:$D$504,Transactions!$C$5:$C$504,$A105,Transactions!$F$5:$F$504,1,Transactions!$G$5:$G$504,YEAR(Setup!$B$18)) -> 100 | D106: =SUMIFS(Transactions!$D$5:$D$504,Transactions!$C$5:$C$504,$A105,Transactions!$F$5:$F$504,2,Transactions!$G$5:$G$504,YEAR(Setup!$B$18)) -> 0 | E106: =SUMIFS(Transactions!$D$5:$D$504,Transactions!$C$5:$C$504,$A105,Transactions!$F$5:$F$504,3,Transactions!$G$5:$G$504,YEAR(Setup!$B$18)) -> 0 | F106: =SUMIFS(Transactions!$D$5:$D$504,Transactions!$C$5:$C$504,$A105,Transactions!$F$5:$F$504,4,Transactions!$G$5:$G$504,YEAR(Setup!$B$18)) -> 0 | G106: =SUMIFS(Transactions!$D$5:$D$504,Transactions!$C$5:$C$504,$A105,Transactions!$F$5:$F$504,5,Transactions!$G$5:$G$504,YEAR(Setup!$B$18)) -> 0 | H106: =SUMIFS(Transactions!$D$5:$D$504,Transactions!$C$5:$C$504,$A105,Transactions!$F$5:$F$504,6,Transactions!$G$5:$G$504,YEAR(Setup!$B$18)) -> 0 | I106: =SUMIFS(Transactions!$D$5:$D$504,Transactions!$C$5:$C$504,$A105,Transactions!$F$5:$F$504,7,Transactions!$G$5:$G$504,YEAR(Setup!$B$18)) -> 0 | J106: =SUMIFS(Transactions!$D$5:$D$504,Transactions!$C$5:$C$504,$A105,Transactions!$F$5:$F$504,8,Transactions!$G$5:$G$504,YEAR(Setup!$B$18)) -> 0 | K106: =SUMIFS(Transactions!$D$5:$D$504,Transactions!$C$5:$C$504,$A105,Transactions!$F$5:$F$504,9,Transactions!$G$5:$G$504,YEAR(Setup!$B$18)) -> 0 | L106: =SUMIFS(Transactions!$D$5:$D$504,Transactions!$C$5:$C$504,$A105,Transactions!$F$5:$F$504,10,Transactions!$G$5:$G$504,YEAR(Setup!$B$18)) -> 0 | M106: =SUMIFS(Transactions!$D$5:$D$504,Transactions!$C$5:$C$504,$A105,Transactions!$F$5:$F$504,11,Transactions!$G$5:$G$504,YEAR(Setup!$B$18)) -> 0 | N106: =SUMIFS(Transactions!$D$5:$D$504,Transactions!$C$5:$C$504,$A105,Transactions!$F$5:$F$504,12,Transactions!$G$5:$G$504,YEAR(Setup!$B$18)) -> 0 | O106: =SUM(C106:N106) -> 100
B107: Difference | C107: =C106-C105 -> 0 | D107: =D106-D105 -> -100 | E107: =E106-E105 -> -100 | F107: =F106-F105 -> -100 | G107: =G106-G105 -> -100 | H107: =H106-H105 -> -100 | I107: =I106-I105 -> -100 | J107: =J106-J105 -> -100 | ... O107: =O106-O105 -> -1100
A108: =Setup!A44 -> Miscellaneous | B108: Budget | C108: =Setup!C44 -> 80 | D108: =Setup!C44 -> 80 | E108: =Setup!C44 -> 80 | F108: =Setup!C44 -> 80 | G108: =Setup!C44 -> 80 | H108: =Setup!C44 -> 80 | I108: =Setup!C44 -> 80 | J108: =Setup!C44 -> 80 | K108: =Setup!C44 -> 80 | L108: =Setup!C44 -> 80 | M108: =Setup!C44 -> 80 | N108: =Setup!C44 -> 80 | O108: =SUM(C108:N108) -> 960
B109: Actual | C109: =SUMIFS(Transactions!$D$5:$D$504,Transactions!$C$5:$C$504,$A108,Transactions!$F$5:$F$504,1,Transactions!$G$5:$G$504,YEAR(Setup!$B$18)) -> 0 | D109: =SUMIFS(Transactions!$D$5:$D$504,Transactions!$C$5:$C$504,$A108,Transactions!$F$5:$F$504,2,Transactions!$G$5:$G$504,YEAR(Setup!$B$18)) -> 55 | E109: =SUMIFS(Transactions!$D$5:$D$504,Transactions!$C$5:$C$504,$A108,Transactions!$F$5:$F$504,3,Transactions!$G$5:$G$504,YEAR(Setup!$B$18)) -> 0 | F109: =SUMIFS(Transactions!$D$5:$D$504,Transactions!$C$5:$C$504,$A108,Transactions!$F$5:$F$504,4,Transactions!$G$5:$G$504,YEAR(Setup!$B$18)) -> 0 | G109: =SUMIFS(Transactions!$D$5:$D$504,Transactions!$C$5:$C$504,$A108,Transactions!$F$5:$F$504,5,Transactions!$G$5:$G$504,YEAR(Setup!$B$18)) -> 0 | H109: =SUMIFS(Transactions!$D$5:$D$504,Transactions!$C$5:$C$504,$A108,Transactions!$F$5:$F$504,6,Transactions!$G$5:$G$504,YEAR(Setup!$B$18)) -> 0 | I109: =SUMIFS(Transactions!$D$5:$D$504,Transactions!$C$5:$C$504,$A108,Transactions!$F$5:$F$504,7,Transactions!$G$5:$G$504,YEAR(Setup!$B$18)) -> 0 | J109: =SUMIFS(Transactions!$D$5:$D$504,Transactions!$C$5:$C$504,$A108,Transactions!$F$5:$F$504,8,Transactions!$G$5:$G$504,YEAR(Setup!$B$18)) -> 0 | K109: =SUMIFS(Transactions!$D$5:$D$504,Transactions!$C$5:$C$504,$A108,Transactions!$F$5:$F$504,9,Transactions!$G$5:$G$504,YEAR(Setup!$B$18)) -> 0 | L109: =SUMIFS(Transactions!$D$5:$D$504,Transactions!$C$5:$C$504,$A108,Transactions!$F$5:$F$504,10,Transactions!$G$5:$G$504,YEAR(Setup!$B$18)) -> 0 | M109: =SUMIFS(Transactions!$D$5:$D$504,Transactions!$C$5:$C$504,$A108,Transactions!$F$5:$F$504,11,Transactions!$G$5:$G$504,YEAR(Setup!$B$18)) -> 0 | N109: =SUMIFS(Transactions!$D$5:$D$504,Transactions!$C$5:$C$504,$A108,Transactions!$F$5:$F$504,12,Transactions!$G$5:$G$504,YEAR(Setup!$B$18)) -> 0 | O109: =SUM(C109:N109) -> 55
...

Sheet Net Worth
A1: Net Worth
A2: Type each account balance at month end. Totals, net worth, and month-over-month change calculate on their own.
A4: Category | B4: Jan | C4: Feb | D4: Mar | E4: Apr | F4: May | G4: Jun | H4: Jul | I4: Aug | J4: Sep | K4: Oct | L4: Nov | M4: Dec
A5: ASSETS
A6: Cash | B6: 8500 | C6: 8720 | D6: 8600 | E6: 8950 | F6: 9100 | G6: 9300 | H6: 9250 | I6: 9500 | J6: 9700 | K6: 9850 | L6: 10100 | M6: 10400
A7: Savings | B7: 5000 | C7: 5200 | D7: 5400 | E7: 5600 | F7: 5800 | G7: 6000 | H7: 6200 | I7: 6400 | J7: 6600 | K7: 6800 | L7: 7000 | M7: 7200
A8: Investments (brokerage) | B8: 12000 | C8: 12400 | D8: 12850 | E8: 12700 | F8: 13200 | G8: 13650 | H8: 14100 | I8: 13950 | J8: 14500 | K8: 15000 | L8: 15450 | M8: 16000
A9: Retirement (401k or IRA) | B9: 45000 | C9: 45700 | D9: 46500 | E9: 47100 | F9: 47900 | G9: 48800 | H9: 49500 | I9: 50200 | J9: 51100 | K9: 51900 | L9: 52700 | M9: 53600
A10: Home Value | B10: 450000 | C10: 450000 | D10: 450500 | E10: 450500 | F10: 451000 | G10: 451000 | H10: 451500 | I10: 452000 | J10: 452000 | K10: 452500 | L10: 453000 | M10: 453500
A11: Vehicles | B11: 22000 | C11: 21850 | D11: 21700 | E11: 21550 | F11: 21400 | G11: 21250 | H11: 21100 | I11: 20950 | J11: 20800 | K11: 20650 | L11: 20500 | M11: 20350
A12: Other Assets | B12: 2000 | C12: 2000 | D12: 2000 | E12: 2000 | F12: 2000 | G12: 2000 | H12: 2000 | I12: 2000 | J12: 2000 | K12: 2000 | L12: 2000 | M12: 2000
A13: Total Assets | B13: =B6+B7+B8+B9+B10+B11+B12 -> 544500 | C13: =C6+C7+C8+C9+C10+C11+C12 -> 545870 | D13: =D6+D7+D8+D9+D10+D11+D12 -> 547550 | E13: =E6+E7+E8+E9+E10+E11+E12 -> 548400 | F13: =F6+F7+F8+F9+F10+F11+F12 -> 550400 | G13: =G6+G7+G8+G9+G10+G11+G12 -> 552000 | H13: =H6+H7+H8+H9+H10+H11+H12 -> 553650 | I13: =I6+I7+I8+I9+I10+I11+I12 -> 555000 | ... M13: =M6+M7+M8+M9+M10+M11+M12 -> 563050
A15: LIABILITIES
A16: Mortgage Balance | B16: 340000 | C16: 339620 | D16: 339236 | E16: 338848 | F16: 338456 | G16: 338060 | H16: 337660 | I16: 337256 | J16: 336848 | K16: 336436 | L16: 336020 | M16: 335600
A17: Auto Loan Balance | B17: 14000 | C17: 13700 | D17: 13400 | E17: 13100 | F17: 12800 | G17: 12500 | H17: 12200 | I17: 11900 | J17: 11600 | K17: 11300 | L17: 11000 | M17: 10700
A18: Student Loan Balance | B18: 26000 | C18: 25850 | D18: 25700 | E18: 25550 | F18: 25400 | G18: 25250 | H18: 25100 | I18: 24950 | J18: 24800 | K18: 24650 | L18: 24500 | M18: 24350
A19: Credit Card Balance | B19: 1200 | C19: 900 | D19: 1500 | E19: 1100 | F19: 800 | G19: 1300 | H19: 950 | I19: 1050 | J19: 700 | K19: 1150 | L19: 900 | M19: 600
A20: Other Liabilities | B20: 500 | C20: 400 | D20: 300 | E20: 200 | F20: 100 | G20: 0 | H20: 0 | I20: 0 | J20: 0 | K20: 0 | L20: 0 | M20: 0
A21: Total Liabilities | B21: =B16+B17+B18+B19+B20 -> 381700 | C21: =C16+C17+C18+C19+C20 -> 380470 | D21: =D16+D17+D18+D19+D20 -> 380136 | E21: =E16+E17+E18+E19+E20 -> 378798 | F21: =F16+F17+F18+F19+F20 -> 377556 | G21: =G16+G17+G18+G19+G20 -> 377110 | H21: =H16+H17+H18+H19+H20 -> 375910 | I21: =I16+I17+I18+I19+I20 -> 375156 | ... M21: =M16+M17+M18+M19+M20 -> 371250
A23: Net Worth | B23: =B13-B21 -> 162800 | C23: =C13-C21 -> 165400 | D23: =D13-D21 -> 167414 | E23: =E13-E21 -> 169602 | F23: =F13-F21 -> 172844 | G23: =G13-G21 -> 174890 | H23: =H13-H21 -> 177740 | I23: =I13-I21 -> 179844 | ... M23: =M13-M21 -> 191800
A24: Month-over-Month Change | B24: ="" | C24: =C23-B23 -> 2600 | D24: =D23-C23 -> 2014 | E24: =E23-D23 -> 2188 | F24: =F23-E23 -> 3242 | G24: =G23-F23 -> 2046 | H24: =H23-G23 -> 2850 | I24: =I23-H23 -> 2104 | J24: =J23-I23 -> 2908 | ... M24: =M23-L23 -> 3470
A26: Sample balances describe the same fictional household earning about $7,800 a month. Replace every blue cell with your own account balances.

Sheet Debt Payoff
A1: Debt Payoff
A2: Compare paying debts fastest by highest interest rate (avalanche) against smallest balance first (snowball).
A4: DEBTS (up to 6)
A5: Debt Name | B5: Balance | C5: Annual Rate % | D5: Minimum Payment | E5: Avalanche Rank | F5: Snowball Rank
A6: Credit Card A | B6: 4200 | C6: 0.2299 | D6: 130 | E6: =IF($B6="","",RANK($C6,$C$6:$C$11,0)) -> 1 | F6: =IF($B6="","",RANK($B6,$B$6:$B$11,1)) -> 3
A7: Credit Card B | B7: 1800 | C7: 0.1999 | D7: 60 | E7: =IF($B7="","",RANK($C7,$C$6:$C$11,0)) -> 2 | F7: =IF($B7="","",RANK($B7,$B$6:$B$11,1)) -> 1
A8: Auto Loan | B8: 14000 | C8: 0.065 | D8: 350 | E8: =IF($B8="","",RANK($C8,$C$6:$C$11,0)) -> 4 | F8: =IF($B8="","",RANK($B8,$B$6:$B$11,1)) -> 4
A9: Student Loan | B9: 26000 | C9: 0.05 | D9: 220 | E9: =IF($B9="","",RANK($C9,$C$6:$C$11,0)) -> 5 | F9: =IF($B9="","",RANK($B9,$B$6:$B$11,1)) -> 5
A10: Personal Loan | B10: 3000 | C10: 0.105 | D10: 110 | E10: =IF($B10="","",RANK($C10,$C$6:$C$11,0)) -> 3 | F10: =IF($B10="","",RANK($B10,$B$6:$B$11,1)) -> 2
E11: =IF($B11="","",RANK($C11,$C$6:$C$11,0)) | F11: =IF($B11="","",RANK($B11,$B$6:$B$11,1))
A13: Extra Monthly Payment (goes to the top-ranked debt in each strategy) | D13: 300
A15: Avalanche Strategy (highest interest rate first)
A16: Debt Name | B16: Payment Used | C16: Months to Payoff | D16: Total Interest Paid
A17: =IF($B6="","",$A6) -> Credit Card A | B17: =IF($B6="","",$D6+IF(E6=1,$D$13,0)) -> 430 | C17: =IF($B6="","",IFERROR(ROUNDUP(NPER($C6/12,-B17,$B6),0),"check payment")) -> 11 | D17: =IF($B6="","",IFERROR(ROUND(C17*B17-$B6,2),"check payment")) -> 530
A18: =IF($B7="","",$A7) -> Credit Card B | B18: =IF($B7="","",$D7+IF(E7=1,$D$13,0)) -> 60 | C18: =IF($B7="","",IFERROR(ROUNDUP(NPER($C7/12,-B18,$B7),0),"check payment")) -> 42 | D18: =IF($B7="","",IFERROR(ROUND(C18*B18-$B7,2),"check payment")) -> 720
A19: =IF($B8="","",$A8) -> Auto Loan | B19: =IF($B8="","",$D8+IF(E8=1,$D$13,0)) -> 350 | C19: =IF($B8="","",IFERROR(ROUNDUP(NPER($C8/12,-B19,$B8),0),"check payment")) -> 46 | D19: =IF($B8="","",IFERROR(ROUND(C19*B19-$B8,2),"check payment")) -> 2100
A20: =IF($B9="","",$A9) -> Student Loan | B20: =IF($B9="","",$D9+IF(E9=1,$D$13,0)) -> 220 | C20: =IF($B9="","",IFERROR(ROUNDUP(NPER($C9/12,-B20,$B9),0),"check payment")) -> 164 | D20: =IF($B9="","",IFERROR(ROUND(C20*B20-$B9,2),"check payment")) -> 10080
A21: =IF($B10="","",$A10) -> Personal Loan | B21: =IF($B10="","",$D10+IF(E10=1,$D$13,0)) -> 110 | C21: =IF($B10="","",IFERROR(ROUNDUP(NPER($C10/12,-B21,$B10),0),"check payment")) -> 32 | D21: =IF($B10="","",IFERROR(ROUND(C21*B21-$B10,2),"check payment")) -> 520
A22: =IF($B11="","",$A11) | B22: =IF($B11="","",$D11+IF(E11=1,$D$13,0)) | C22: =IF($B11="","",IFERROR(ROUNDUP(NPER($C11/12,-B22,$B11),0),"check payment")) | D22: =IF($B11="","",IFERROR(ROUND(C22*B22-$B11,2),"check payment"))
A23: Avalanche Strategy (highest interest rate first) Totals | C23: =MAX(C17:C22) -> 164 | D23: =SUM(D17:D22) -> 13950
A25: Snowball Strategy (smallest balance first)
A26: Debt Name | B26: Payment Used | C26: Months to Payoff | D26: Total Interest Paid
A27: =IF($B6="","",$A6) -> Credit Card A | B27: =IF($B6="","",$D6+IF(F6=1,$D$13,0)) -> 130 | C27: =IF($B6="","",IFERROR(ROUNDUP(NPER($C6/12,-B27,$B6),0),"check payment")) -> 51 | D27: =IF($B6="","",IFERROR(ROUND(C27*B27-$B6,2),"check payment")) -> 2430
A28: =IF($B7="","",$A7) -> Credit Card B | B28: =IF($B7="","",$D7+IF(F7=1,$D$13,0)) -> 360 | C28: =IF($B7="","",IFERROR(ROUNDUP(NPER($C7/12,-B28,$B7),0),"check payment")) -> 6 | D28: =IF($B7="","",IFERROR(ROUND(C28*B28-$B7,2),"check payment")) -> 360
A29: =IF($B8="","",$A8) -> Auto Loan | B29: =IF($B8="","",$D8+IF(F8=1,$D$13,0)) -> 350 | C29: =IF($B8="","",IFERROR(ROUNDUP(NPER($C8/12,-B29,$B8),0),"check payment")) -> 46 | D29: =IF($B8="","",IFERROR(ROUND(C29*B29-$B8,2),"check payment")) -> 2100
A30: =IF($B9="","",$A9) -> Student Loan | B30: =IF($B9="","",$D9+IF(F9=1,$D$13,0)) -> 220 | C30: =IF($B9="","",IFERROR(ROUNDUP(NPER($C9/12,-B30,$B9),0),"check payment")) -> 164 | D30: =IF($B9="","",IFERROR(ROUND(C30*B30-$B9,2),"check payment")) -> 10080
A31: =IF($B10="","",$A10) -> Personal Loan | B31: =IF($B10="","",$D10+IF(F10=1,$D$13,0)) -> 110 | C31: =IF($B10="","",IFERROR(ROUNDUP(NPER($C10/12,-B31,$B10),0),"check payment")) -> 32 | D31: =IF($B10="","",IFERROR(ROUND(C31*B31-$B10,2),"check payment")) -> 520
A32: =IF($B11="","",$A11) | B32: =IF($B11="","",$D11+IF(F11=1,$D$13,0)) | C32: =IF($B11="","",IFERROR(ROUNDUP(NPER($C11/12,-B32,$B11),0),"check payment")) | D32: =IF($B11="","",IFERROR(ROUND(C32*B32-$B11,2),"check payment"))
A33: Snowball Strategy (smallest balance first) Totals | C33: =MAX(C27:C32) -> 164 | D33: =SUM(D27:D32) -> 15490
A35: Interest Saved by Using Avalanche Instead of Snowball | D35: =D33-D23 -> 1540
A37: How this is simplified: each debt's months to payoff and interest are calculated on their own with the NPER function, assuming that debt's payment amount never changes.
A38: A true avalanche or snowball plan rolls a paid-off debt's payment into the next debt once it is gone, which clears the whole portfolio faster than the totals shown here. Treat these numbers as a conservative estimate, not an exact payoff date.

Sheet Dashboard
A1: Dashboard
A2: A one-page view, built from the Monthly Budget and Net Worth tabs. Nothing here needs to be typed.
A44: Category Group | B44: YTD Actual Spending
A45: Housing | B45: ='Monthly Budget'!O20 -> 6029
A46: Transport | B46: ='Monthly Budget'!O34 -> 1293
A47: Food | B47: ='Monthly Budget'!O45 -> 1190
A48: Insurance | B48: ='Monthly Budget'!O59 -> 1305
A49: Debt | B49: ='Monthly Budget'!O70 -> 1125
A50: Savings and Investing | B50: ='Monthly Budget'!O84 -> 1500
A51: Personal | B51: ='Monthly Budget'!O101 -> 308
A52: Other | B52: ='Monthly Budget'!O112 -> 155
A54: Chart data above is calculated automatically. Leave it as is.
